{
  "hsc-higher-math-1st-paper-chapter-03-set-02-q01": {
    "correctOption": "1",
    "explanation": "সঠিক উত্তর: গ। $m=(y_2-y_1)/(x_2-x_1)$।"
  },
  "hsc-higher-math-1st-paper-chapter-03-set-02-q02": {
    "correctOption": "$y=5x-14$",
    "explanation": "সঠিক উত্তর: গ। $y-y_1=m(x-x_1)$।"
  },
  "hsc-higher-math-1st-paper-chapter-03-set-02-q03": {
    "correctOption": "$x$-অক্ষে 6, $y$-অক্ষে 5",
    "explanation": "সঠিক উত্তর: গ। Intercept form থেকে সরাসরি ছেদাংশ পাওয়া যায়।"
  },
  "hsc-higher-math-1st-paper-chapter-03-set-02-q04": {
    "correctOption": "$\\frac{59}{\\sqrt{85}}$",
    "explanation": "সঠিক উত্তর: ক। $|ax_1+by_1+c|/\\sqrt{a^2+b^2}$।"
  },
  "hsc-higher-math-1st-paper-chapter-03-set-02-q05": {
    "correctOption": "সমান",
    "explanation": "সঠিক উত্তর: গ। Parallel রেখার slope সমান।"
  },
  "hsc-higher-math-1st-paper-chapter-03-set-02-q06": {
    "correctOption": "$\\frac{-1}{4}$",
    "explanation": "সঠিক উত্তর: গ। লম্ব রেখার ঢালের গুণফল -1।"
  },
  "hsc-higher-math-1st-paper-chapter-03-set-02-q07": {
    "correctOption": "$\\frac{-5}{2}$",
    "explanation": "সঠিক উত্তর: খ। $ax+by+c=0$ হলে slope $-a/b$।"
  },
  "hsc-higher-math-1st-paper-chapter-03-set-02-q08": {
    "correctOption": "$x$-অক্ষ",
    "explanation": "সঠিক উত্তর: খ। $y=$ constant হলে horizontal line।"
  },
  "hsc-higher-math-1st-paper-chapter-03-set-02-q09": {
    "correctOption": "লম্ব",
    "explanation": "সঠিক উত্তর: খ। Perpendicular রেখার slopes product -1।"
  },
  "hsc-higher-math-1st-paper-chapter-03-set-02-q10": {
    "correctOption": "$ab'-a'b=0$",
    "explanation": "সঠিক উত্তর: ক। Parallel হলে coefficient ratio সমান, অর্থাৎ $ab'-a'b=0$।"
  },
  "hsc-higher-math-1st-paper-chapter-03-set-02-q11": {
    "correctOption": "$\\frac{2}{3}$",
    "explanation": "সঠিক উত্তর: ঘ। $m=(y_2-y_1)/(x_2-x_1)$।"
  },
  "hsc-higher-math-1st-paper-chapter-03-set-02-q12": {
    "correctOption": "$y=5x-31$",
    "explanation": "সঠিক উত্তর: ক। $y-y_1=m(x-x_1)$।"
  },
  "hsc-higher-math-1st-paper-chapter-03-set-02-q13": {
    "correctOption": "$x$-অক্ষে 6, $y$-অক্ষে 8",
    "explanation": "সঠিক উত্তর: ঘ। Intercept form থেকে সরাসরি ছেদাংশ পাওয়া যায়।"
  },
  "hsc-higher-math-1st-paper-chapter-03-set-02-q14": {
    "correctOption": "$\\frac{21}{\\sqrt{53}}$",
    "explanation": "সঠিক উত্তর: খ। $|ax_1+by_1+c|/\\sqrt{a^2+b^2}$।"
  },
  "hsc-higher-math-1st-paper-chapter-03-set-02-q15": {
    "correctOption": "সমান",
    "explanation": "সঠিক উত্তর: খ। Parallel রেখার slope সমান।"
  },
  "hsc-higher-math-1st-paper-chapter-03-set-02-q16": {
    "correctOption": "$\\frac{-1}{4}$",
    "explanation": "সঠিক উত্তর: ঘ। লম্ব রেখার ঢালের গুণফল -1।"
  },
  "hsc-higher-math-1st-paper-chapter-03-set-02-q17": {
    "correctOption": "-1",
    "explanation": "সঠিক উত্তর: খ। $ax+by+c=0$ হলে slope $-a/b$।"
  },
  "hsc-higher-math-1st-paper-chapter-03-set-02-q18": {
    "correctOption": "$x$-অক্ষ",
    "explanation": "সঠিক উত্তর: খ। $y=$ constant হলে horizontal line।"
  },
  "hsc-higher-math-1st-paper-chapter-03-set-02-q19": {
    "correctOption": "লম্ব",
    "explanation": "সঠিক উত্তর: ঘ। Perpendicular রেখার slopes product -1।"
  },
  "hsc-higher-math-1st-paper-chapter-03-set-02-q20": {
    "correctOption": "$ab'-a'b=0$",
    "explanation": "সঠিক উত্তর: খ। Parallel হলে coefficient ratio সমান, অর্থাৎ $ab'-a'b=0$।"
  },
  "hsc-higher-math-1st-paper-chapter-03-set-02-q21": {
    "correctOption": "4",
    "explanation": "সঠিক উত্তর: ক। $m=(y_2-y_1)/(x_2-x_1)$।"
  },
  "hsc-higher-math-1st-paper-chapter-03-set-02-q22": {
    "correctOption": "$y=5x-9$",
    "explanation": "সঠিক উত্তর: খ। $y-y_1=m(x-x_1)$।"
  },
  "hsc-higher-math-1st-paper-chapter-03-set-02-q23": {
    "correctOption": "$x$-অক্ষে 6, $y$-অক্ষে 4",
    "explanation": "সঠিক উত্তর: খ। Intercept form থেকে সরাসরি ছেদাংশ পাওয়া যায়।"
  },
  "hsc-higher-math-1st-paper-chapter-03-set-02-q24": {
    "correctOption": "$\\frac{52}{\\sqrt{74}}$",
    "explanation": "সঠিক উত্তর: ক। $|ax_1+by_1+c|/\\sqrt{a^2+b^2}$।"
  },
  "hsc-higher-math-1st-paper-chapter-03-set-02-q25": {
    "correctOption": "সমান",
    "explanation": "সঠিক উত্তর: গ। Parallel রেখার slope সমান।"
  }
}
