[
  {
    "image_url": "https://i0.wp.com/en.lekhaporabd.net/wp-content/uploads/2022/10/Lekhapora-BD.png?fit=150%2C90&amp;quality=100&amp;ssl=1",
    "text": "Sv\n¥ oesT\nee.)"
  },
  {
    "image_url": "https://i0.wp.com/en.lekhaporabd.net/wp-content/uploads/2017/06/Lekhapora-bd.png?fit=200%2C90&amp;quality=100&amp;ssl=1",
    "text": "& &\nSomer"
  },
  {
    "image_url": "https://i0.wp.com/en.lekhaporabd.net/wp-content/uploads/2023/08/HSC-Physics-2nd-MCQ.png?resize=804.999999996%2C453&#038;quality=100&#038;ssl=1",
    "text": "sidffeat GHA\nHO McQ sw"
  },
  {
    "image_url": "https://i0.wp.com/i.postimg.cc/2mWSfGyv/1.jpg?resize=804.999999996%2C1138&#038;quality=100&#038;ssl=1",
    "text": "fre oY 3@89/030\nTET errr\n—— fren: [1]7]s]\nBI IE\n(20% Hore rap wR on [=]\nTne ff\norfr—e\n_—\n(RET 8: —orrrege wafrdf ww Sw av we TG Role amg whe we ws\nF/T Saw TI TT Tes ery wr ry SAM FW | fel avg wa S 1)\nPeo CIC ery wiht ORT WE A |\n31 cm fe efit sen sere iE ce a1 fom afew Lo Rees ws wef gem www\nFora ww an— wa wre fs 2 war\n® crew\n@) er Som A(+10C) B(+15C)\n(1) SET Bem 2\naE Sw ”\n1 ERE  earen—\ni OW CRIA A GR TN\nii, ered efi a cae afd C(-12C) D(?)\nww\niii, wereyad} afr a=Gft fig aicE @ -15¢C ®-ic\nbri (ivi 2) oc\nie\noN) iii 9) hii git vi Sf or fo aver\n(®) ww [ORIN\nFre SRT SCE © © SR STO BE We: on) fe eam fps wmam\naf wo ei lr ora | wet wow se » > a coon ey\nIt aR ST 30 k FH add\n. B= 8 wi.\nOf) Fre mor\n© wm weet Fer 4 oT 0 Fp\n* 80% 0) 75% 01 18Q CTW @=T wifitm 2A Sf am\non 33% ® 5% ATT FAS A | 20A SYR STR TH TT\nTE GI MT TA TS Tr\n~ 81, \"WTR IA we 008 Q © o1Q\n@ 60k ) 90k 02Q Ws\n@ 120k 0, 130K 531 Sof Te af Te wr AES\nego vam fe fev — TH WR A CT effdFTr\nfs (¥) wre\n® ww we ® re (@ afew\non) wer sa) TT Tey wm\n1 EE Em— I ROT af wT aw wT\ni co fry Bie Coon eTTen i, STOTT ACY Wf TY WOT\nii. wifer sre cwon srcares ww afer for Fosfor wo\nHL. moon Do feds wor Jit, AFR SCR SR FT TAN\nres com fer Pe Casal\n@ isi 0) isi @® i* 0 iii\non sii ® iio on dei ) iii\nHSC & Admission $%w-3am Io ht ey"
  },
  {
    "image_url": "https://i0.wp.com/i.postimg.cc/rT3wb3VM/2.jpg?resize=804.999999996%2C1138&#038;quality=100&#038;ssl=1",
    "text": "Soi fifoy wie fog aby rm fro ave oY R01 fs rer ref wow 2afiiey wm\n=e <r A feet 31 gee comm oy FS TI (®) aS oy wr dl\n@ sofifss ara (2) fafa 1 goo\n} Ei g To\n® fotmr © wom om sh\n381 GPW WN ol Tow own Crane Ren 1 cE AR INE cv wa gre zw\npnbol (¥) wer (=) fo\n7) Tew Srey\n(%) Ife dw wr ® ™ ®\n1) er SE Raf FEE Rim Tafs dm\n@ wFeEum @) Fe\nsei Sy ordre we rife ww cot? @) wf sr\n@ wrw (m) wer\n(¥) weft i\n(Sos fem ® =\n0) Fw Ret R01 Fis fe ars dne—\nPGE i ee — Lo fees\ni Ee | (¥) STO Sf fran raf wren Ba & wl fire\neae | @) wh Yow Frwew Tr ames footed\nLain autsind , SCT FOS Tf Freon com fdr\nca grew we fw | (DFT SRR eran wer Stet or @) iii [COREY]\npaskiatoa gl PY boob OW iy ® ici ® iii\nNo ea. Produit x.\npostagitio bial 281 X-OR «¥ ede comfy\nFico RMIT WITTE 39 © Sh, eto Ber me + =)\n6600 4 wm rot stom onus ®\nTH | CHIT To tend 6800 4 Pes\nFTF h=663% 10 5 © iy [4] =>\n391 SrfeE CTR ii wy\n® 342x108; Wm =e\n(1) 332x108)\n©® oxi\n® 2925x1019) 2 =D\nsv 1 Fiers orale ff vor\n@) 5939x1021 3 Trlmd\n® s9x102, - 0 fenees STR\n() 5939x1019) 20 b--/1 -\n23 MA er Vi (volt)\n31 SPI] TCT A Seton] cori\ni ROR FRR TP wy www pees\nii. Affe 1 C1 Re wore\nJR OR ~ Lod\niil, TORIC PEG fff gpd Sorc afd STRTST 1 ~ V caf orien\nFo cad A =o 1 ween 1 Ge wT\n® isi A ® os [ET\non drei hie ™ s70 ® 150\nHSC & Admission $%w-3aE"
  },
  {
    "image_url": "https://i0.wp.com/i.postimg.cc/mL6kpBYC/1.jpg?resize=804.999999996%2C1138&#038;quality=100&#038;ssl=1",
    "text": "RT 30 3/2030\nwef wet\nnde was: [1 [7] s]\nAHR QE\n[RoR ove Frcerapr weg. of:\nTe ff\nfe\nRote aby « were wR wn Sor dum whe TE Rede a TET JET Te\nfredegs Sowa Jaf av ford wer ww rm wai ww | fe et ww 3 1]\nerp CHT ew w/o ore we |\n31 CRTC SHY FetaTTE A Mr — © Togs fee wer\n@) 270° (¥) 180° @ 5454x1071\n9° or (0 sasaxiotdy\nfive wa er fre (h) S45ax107%)\nv i on ccs cw (@ 5454x107\ni ExB af al amu\niii. Eo B Sem ame we www mn), 1605710 7g\n® 1:66057x10 kg\nolor - on) 1-6607x102kg\nisi iii 10-27\no) isi @ i iisii Tie\nbi TREE EE oF (TR WF RoR\nel bree IE EER eve Fem of\n(® wri [CR I=\n@ one fe fm 2h 3h\n(1) wf wom rl [ist oT\n@) ww dn\nB1 COW WEN WPTE REE EH n-th\n81 FEA wow Rov ors fe e fre few\ni wef fm of we mm we\nih, SUPT SS FER wwe! ame @ 18 «© 14\ni, wr elf ® 12- ® 21\nFrrsw cod ssw\n@® iii @ iii S01 (A+B) (B+A) aww\n(1) ii wii @ i isii pt lial\n- () AB+ AB\nFATS BRT SCF ¢ © Se 20 Be « (i) A®B\niii. A+B\narf Tomi Tw ffs ew 9.1x1030kg\nwe aw 80% afer we | Fo oul ive he\n® ivi (9) die iii\neTown er o) iii ®@ i, iii\n®. 151610 0kg 331 ols me er Prades eres 80,\n(0) 2:52x10%0kg PTR eT 9-8 mA TW, Treo As erg wr\n(0) 1516x100 kg ® 014mA (%) 013 mA -\n(®) 252x1020kg ® oma ®) 0-11 mA\n[ora ob ¥y\nHSC & Admission $HN-SEE"
  },
  {
    "image_url": "https://i0.wp.com/i.postimg.cc/FrK1x7Lh/2.jpg?resize=804.999999996%2C1138&#038;quality=100&#038;ssl=1",
    "text": "31 P-bit cfs Rope eames wd — 5» | rue wera LafiRy qeTm—\n(®) omy i TE we FT RTE Co\n@) Tora Ei\n(1) caf ii, fre wren wma fee ae |\n@ a iii, fe wor of wo crore THT\nso FAUST IW 1afere Frew wf fr al\n@ fewer (¥) f@em favs cori far\n¢) ww (W) wwe @) isi @ isii\npg - we do ©) igi ) i, disiii\nNfs sffiere FCs afm fad For firs BRT ACTF 08 RY TN AT\n@® sax Soa :\n(¥) 492x102 JK! L100\n(mn 492x10° JK!\n(®) 492x103 KIK™! (4 wn]\nSe CHRR SPEC CFE— . - =\ni ered fs fee Hl}\nii TEs ef Brdoy\nii, ATO Som fd Re ]\nfiw cated Afar 17 20\n@ isii (%) di sii 30 ons\n@ viii () i, ii 9 iii Io) $a ® a .\nEi]\nSui he oR oi for hr\n[@) mad ® >>],\n@ sos @ 11>\n(®) wera @ dy > 13],\nfsa SRL SITE 39 Sb A ® L>1>1\nSomes Rf IE swears Fela maT T0g—\nCy =204F  C,=60uF i sw om sree rere Rf ert ww\n— ih, wom fe few rareet ffs ent\nEc\ni iii, qa Tees ere Af ew wT\nI ws GE sw?\n100V ® iii ®) iii\ni @ ii (9) i, ii 8 iii\n341 EE HRY Er R01 Firsw cer cay wffcet Tre Tne\n@) 80uF (*) wife (¥) comfibm\n@) 204F ® omdw (%) cawfivm\n[J 1p 381 oT fs 1 Tem—\n© T5HF ® @a-n}  ® evn}\nSo HERE Ree A wee— my 2\n@ 1:3- 0.5 LA\n2 i xe afew ow wrE—\n4 ee (®) worn (@).\n@ 3:1 @ sme (v) afew\nHSC & Admission $HN-SEE"
  },
  {
    "image_url": "https://i0.wp.com/i.postimg.cc/VYJkS3QN/1.jpg?resize=804.999999996%2C1139&#038;quality=100&#038;ssl=1",
    "text": "it we 3¢93/3030\nPe ww\npo wee: [17] ]\nfw om\nTAFT QC soem | om [2]\nnse RFD\nhme\nee\n[Rom 2¥0 + rT Te ww Se do wf To Flic er THOETS TOE TE\nA /rCdg® Seca ud TT ICED PR VA rp AD a 1 affofl era 1 > 1)\nereTGE CRTC ere M/E or we A\n31 0 zy sv wm sche hy fo VT ¢ 1 we EG ©\n® 024 ® 03A -\n(0 044A ® 5A or di)\nugar  g CC ty\nQn\n=i\npl ON _i2¢ ¢1 Bf AC ax 9R ems fife fre Vv, To—\nire afows ave 0 cv feo TT on hn onsh bocd\nTT gd Nf fr D cB FS oe eT [ +B oR ar | CF TR\ns we Tr peng\n.@ -3c 2c he\nmM 6C om 8C ©) SRE wD wf 1%\nre ff QD 1% cm\n. el tad @ ~~ [OR od\nr om = 9 at\nA hv B\n® a1 Few am ord afi cen dQ = dW\n3v wn\nE (®) Tot @ =\nNy (1 werd (%) rsmre\nfom Ae B fm moe Simms =e ws vi oP sifefe Tre TE TO BT «IEE Wwe aw\n@ 27V WV TT STO FC TH TH\n\" on 6V @3v @ wey\nfre\n81 Soren qufte « Sw E TO— 1 firs fs\ni dsing,=nh [VI\ni sind, =n DY *\nji. (a+b) sin, =nh B15 iE wp ft wa a fire afte\nwr Tw ats Sew fem Im wor\nfrm co wr Sefer fa wer\n@® ivi @ ivii @® Vim im\nCn disiii 09 i fieill 0) 2m ® 3m\nfora brave\nHSC & Admission $5w-3aE"
  },
  {
    "image_url": "https://i0.wp.com/i.postimg.cc/t9CTbsBW/2.jpg?w=804&#038;quality=100&#038;ssl=1",
    "text": "TON AG\nN\noi fom aw yom we BT CT Ee ——\nB=(f sf +eh) ne Cuaoduata\nv ® if / ®\nnp np\n[Q) ®\nX tn] nt\nz forse cova corm de © du ew BE Whe:\nfyrwam ZX wT gre 40m? cw a\nfafvi® wor fe pr FS? N\n@ oNmC! 2\n(%) 80NmZC™! 0-5N,\n@ 200Nmc! B ©\n() 240 Nm?C™! A 1\n331 efficars me fe ffm FCs oE— i:\nPres set bis ?\nin So HovT\n(0 06931\nii, ww PrvT ver\nfresn comfS fy ® A\n@®) ieii A\n@ iii © 5693\nmn raw sei ®ve Bw For\n(%) i, ii iii @) 06N,\nSa wee win foe «wf crbew Efe 0:12 N,\nEm — 037N,\n[RE ®) 006N, .\nb 3a) nfm ARE cw cleft TEE FE nO\nio P=3 Sard owt mr\n. h @ am (0) forms\nw v=td @ form () Bm\nFro cd owe v1 from cere fom wfpgrrar cdi wr\n@ isi\nof iii ™®\non) iii ®\n@ ici\n301 TTR TH NOW ww ow RoraGen ©\n- <b,\nob nthe, E\npp\nTt ® x\n9 8n?hie?\n©\n® ®\n© rr re\nHSC & Admission $5w-3egE"
  },
  {
    "image_url": "https://i0.wp.com/i.postimg.cc/cd9JLdzj/3.jpg?w=804&#038;quality=100&#038;ssl=1",
    "text": "JON TE\n°\nmi 201 Tm a fhy hwn gd wwe www\n3 CT SIAC TG 4 oy wr\n3 Ne ® 2\nPy | 7\nim 7\noY 3\nfou ab cmefbaf® fivft ww— ® 2\n@) Tm (¥) re 2\nLass Ld 81\n0 SAR TAYE GNWR GFF TH— A\n® Am R Q\n® Am?\n™ Ad A c\n® Alm? R s\n2B) CORA CoE Ge ef FE GTN, | o\nTE RN FRG oF AE ry\nlp Xe) fom RROTOw Gram firey srg we Fi\n@ t=3hn ®) t=2ln\nA N -\n® on 4 ove\naw, N, ™ vemve\nx1 Fo fou ced n-p-n BifeEOT? ® Vp=Vc\n® C we 14mAY\n250 -\ni ped\n150 4 ®\nc 10 H\n® Fs 50° 54 H\n* HERRERA\nB\no A\nBhvrrEn AB wat mdi are Fer\nEB @® 07150\n® ® no\n(1 2660Q\na Wr 49\n: HSC & Admission $5w-3ege"
  },
  {
    "image_url": "https://i0.wp.com/i.postimg.cc/CwBp82sP/1.jpg?resize=804.999999996%2C1139&#038;quality=100&#038;ssl=1",
    "text": "Ties. = 3@99/3030\nfriar Sr\nFro\n= -\nBA AT ose Pere ty\nxe fifD ~~ =\nfir—e\nJ TE — Ee\n[Rete G8: TES Wn why SOE SUH WE av fli ar rire emg\nTCE? ST Jaf we oD PT Tf ls | offs ecw ws] hi\nepi CIC Sr P/E ort we ay\nS120 LR rer Fs ca Da wan fA? a1 Fo Com ceive wer\nor ga Ca @ me\n® 0 swim (©) ww\n1 af FE 2a wer 60% | af or ort vi «fe confi aim off aw 6 3 pwn\nARTE SHAT 17°C 7 Or Ser SI Reet 70 | TE Qe “tee eA (2)\nLowe © STRAT (A) FTA TE—\n@) 725°C (¥) 700°C @ (A+5),2Z-1)\n@ 2c ® 290°C 0) (A-35),@+1)\n“ ® a-».cz-»\no| «of GHrte fem, Fe mA (%) (A-8),Z+1)\ncoffe «¥ San Tre D , Dp @ Do T 51 9 OEE 50°C SWE GR SQ aR\nfui 100°C STHRIIT GIR 6Q 10°C Tra\n(#) D,=Dp=D (9 D <D, =D; oir\n¢) D.>Dy>D; @ De>De>Dy @ 12 @ 20\n81 ww aN fie (oF = a) ATTA ST mm 3Q @ «©\nWAT SIE TOT 0 WTS GRIT SATE so fit GAD comfErmem aw wwe\nSr ef TT) ew Ew fy TE ® «= @) FEE\n— [OR cw\n() Asind=a (¥) acosd=A 53 1 Fa cms sm afi fy\n@ asid=) (9 AcosB=a (7) FE SE\nno @) We STS\n[3 oof wae ofp Rega To rd trey = @& Fp,\n21 & FreguT TO e oe wT (0) efter sf? wre Am\nLN @) 2: (iii) 70 1 re FRYGTY\n® 3 @ 2 1 Rad py | i) wT\n™) 3 0 ELS i RST iB YA | ere me rw ac Regd\n2 i, EMSw wR | TS AR\n1 re EE am owen fiom com FS fr iii, efi sre spare siteut WE A\nar wo core sive\n4 pi a2 ail @ ivi @ iii\n©) isi iii\n' HSC & Admission $%W-SEE"
  },
  {
    "image_url": "https://i0.wp.com/i.postimg.cc/WTfPhVgq/2.jpg?w=804&#038;quality=100&#038;ssl=1",
    "text": "soi y= amo cor er REL LE CR e—.\ni s SOE | AT A i 0), —g, 2\n@ o=3R [CECE 20110 Wn Nr Hrs wom\n@ c-2r  ® oem feos cece fre py ory\n2 @® o-~\nFcon SRT oF GR 38 © 3¢ Tan Sox « 0-1\nwe + 0 ge\n«=f RrreGEw Fre oF mg = 9+1x10-3 kg.  o-L\nReeraaf 0-8C Fore ETI q\n381 SR Ep Ror Free =f wer Ww) EF EE gE fl ae rE\n@ 1023x1014 @ s19x1074 Ry > Ry > Ry a, wom 1 Frey ofoe\non s12x1074 4:095x10-143 Ppa\nSer Sr SPT ETE SE oA @ free {cats fom wey Fr eee wn 1, 1p, 1p)\nog SS TO? [ RE A A\n@ 5:4 ® 5:3 CD L<h<l @ L>L>1,\non 5:2 © 5:1 R01 TEE wf qr\nFs SRT oT TAR 36 © 34 TAH i cle Tm\nia ii, WNT SMA IF Se TW EE\nie SIC CTT\nmm i c iif, RCE Aer om\nAe\n8 £2) ew cod afr\nfoa-3 \\ y @) ieii @ ivi\nso foes a vier CER ww BE o) isi ® iii\n@ orc (9 ANDO®\n() NORGE (0 'NAND ces 281 IPT TE ORR FRAT ST Te —\n1\nvai fos a eb Ce fos oF BA I @ Yeon, ® ord\ner fT Cae wer CofED Se Tw? 5\n@ ror () NAND Ch) ko © Fw\n() X-OR (7) AND\nSoi IC eR ST (de fof Te RYE — el “\n@ 9x10°\n) 885x10712\n1\n® 835x102\n1 ¢\n@ 50 f 1 0\nSoi fe SRT SI 9 TE— fs\n@ Am @ va!\n\"Ne ® ict fas @ ewe The 90 aries The\nwel 36W TT 20 Er 93 ess Rew\n01 CO, \"CH OF y 97 TH FT? trey firsa cami?\n® 133 @ 140 @ 2v @ 4v\n™ 167 ® 1.69 o sv ® ww\nHSC & Admission $%W-SEE"
  },
  {
    "image_url": "https://i0.wp.com/i.postimg.cc/YtzWf4Ss/1.jpg?resize=804.999999996%2C1139&#038;quality=100&#038;ssl=1",
    "text": "ret WwW 3280/2039\nTee wer\nstander\n< fd foray cts\ns a [Rox0 om Ferrer swear]\na RET of: =]\nfre\n—\ney: FTE Tin SSR Sur aw wf av Rs ar wre qo Re He rt\nST TT 1 +E TT vA pd wD ww | «fed ew AW 3 1 FP ev Be Five we)\nIG OTR ath vif oven TRA A |\n31 RR TP wf dn 6 awl Fw ot oi Teor fefiy dw ar smd War\nTove «x fre wk wn fs oT (3) @ vom\nm= a () word (%) oft\nPo a1 fess comfdu wants doe wy\n@ Sow oe mA EE (®) wferefiafy\n(%) wom on po Tw © =a\n1 Fos a wd are Sure Te ww? * do .\n(®) off\n@ vm vi eR eR Af Re fran ws 1:3;\n(1) = a ofS wer Swfavren ToT AE ©\n(%) Brevln oe\nP— @ 1:4 4:1\n° i cor Ta wR fra aw [URI] pe)\nii. we fie fi ara mem aH al wi ef fem fre derbi Ties\niii. 718 fsa oft ww fe om fife —\nfown cows fier a Ser Fon\n@® isi (@) iia ili dig\non isiii @ ii viii @ Fe 3\nrex Svc WITS 8 © oR HOE BH wre adie\n: do RG RAR «7 FORT TH 0=3 Fw\n100 CF n= ¥¥ Wier eww Fer fifmrr\n, = we wy (fre yw R)\n4 SR\n1, b ° re\nEa [5 ie\nE-3V.re0s0 o 3%\nRE Taper —. eo:\n027A\no 030A M1 I a ETS dev. hw\n0 055A ST SS wen wR\nffs qm 1 —\n(%) 060A >\n(3) 540 nm\n@1 COTE TAA (EFT FE TA (9 400 nm\n7 @ ssv ®) 302v @ 310mm\n©) 275V @ ov (%) 220 nm\nHSC & Admission $%%-SEE"
  },
  {
    "image_url": "https://i0.wp.com/i.postimg.cc/knMtjn6X/2.jpg?resize=804.999999996%2C1139&#038;quality=100&#038;ssl=1",
    "text": "TAT FR A (fe Frm [}\nRemon dah Se — % =096, Tn a\n@® ic ic wre wr\nba tl © i\n® Sc ® Zc 24\n301 CRTC AWE oA A a STA (0 48\nffi are mi afb— Fer In| SARI WIR ONG y OF WF FS?\n@) a- @ tr @) 1:05 [ RE]\nid ® pwn 14 ® 166\n381 au Ferm After rie fp — 201 Frm col wm fim\nMoa ” (7) aft gre wow fim 2\nN+ He— O+x, aU x W193 — (2) syoirfy sro wit rey I\nLo 2 8 (1) otto cramer tet AAT\n-» ped @ Ot SPIRIT I TRAIT ACH\n(on) Rw R31 FEET fF af Remy HER 51 5%\nw) Eibwm fs TT ICT! SST TH FE FCA?\n@=14)\n31 cfm wd 1600 76 1 6400 TE fT @) 25% ® 302%\n) RIT 9 wet ow Wr (1) 476% (®) 5%\n®3 ™F 1 ae m—\n1 1 @ Frobor Regen fmt\n® 5 ®3 (3) wore ww few ager\n“fs Fema rTe\nS91 P- DRY wf oft wm wr Row [W]\nFrac 3c cu il cure a a or (%) fe Bema AwTTer\n() wre 201 afb ag Gad ov we ow Frgw ay\n© sf (® 3x10-15\n©) wwf (®) 4x10-1%C\n[idk @) 576x10-1C\nsar from 76 whos ami? @ 64x101%C\n2, 381 owe wg fw fg ofp m—\ni, SF CR oT Seow Sor Fk wa\nha i, Sew A\nBvan <) Vout iif, a Fra wy\nFes coral fare\n@ isi (Yi\nVou Vou ® ‘sii 9) i, ii @ iii\n™ (E ® =v VN <1 fom og of fr\nVou Vout © av\ncom\n™ boa [J [An So\nHSC & Admission $HW-SER"
  },
  {
    "image_url": "https://i0.wp.com/i.postimg.cc/fDwY0c7p/1.jpg?resize=804.999999996%2C1140&#038;quality=100&#038;ssl=1",
    "text": "wo ar 3¢e3/3030\nweft ww\nerr few oe + [75]\nTEAPRE QE tow\n[2020 iva fivzmamt wer om: [=]\npe ffi\nfee\n——\nRom aban snags wich wfen Sw wore wes wore flies erg afte gene wT\nwm prehg® Boom Told ww Ares we ww woud wud waves wr fel era wy |\nTOR CPR awe fb ort wor an |\nBrel op at 3— WH em Bow rer el [=]\nA ¢ Bl wry: A gr wx 100g am 9 P Q\n1-8 x10%ms™! con sew) B wg wipes Cae]\n1-34,\n246V 1 (S06 $C TR 6.63 x10\" Ms) PR\nSt ge ew weeds wor ® oo @ if\n@) 1.72x 10~%m ™ 20 m 4Q\n7,\n@ s18xi0Tm wi RRs av fos come\n(1) 6:68 107%m Vin? 2\n(0 528x 107%m_ 09; Vow 9 Yo\n™ vm ® vm\nXA gE\nGees 9 x 1018) XK wmdfEmen & (Knee) STbw v2\nii es fe 225 x 10153 on Bey > ov\nii, cam weds wT 7 wofe TE (Mm) 0 07V\n5% TEA CR | RTE TR\noe cot on vi sn [GT\n@® ici ot) isi @) MLTA (® MLT AT\n0 die ) idrsii () MLIT 3A ® MLA\n© fice om fost ofa) ome awd Bi GE (mvTeR off REY IF wn ae\nrE HTT ww wn ers—\n® —p— @® im\n(%) 9x10%m\n© —e— @® 910\n® —D— ® 9x10'\"'m\n™) — Joi REfEe yw Tm—\n81 20ms™! con sha wwly Fo ES cane a\ntien oui won Tr fee wien wars E\n| Tn ow wn wow we of mer w“ =\n(orm sof wo 1260kg~ kl) :\n(® 14873k Im &\n@ 183k fia coral amr\n(mn 18573k @ ici (0 Pei\n(%) 18673k © dieu 9) ii eiii\nHSC & Admission $%W-SEE"
  },
  {
    "image_url": "https://i0.wp.com/i.postimg.cc/JMPZ3sPn/2.jpg?w=804&#038;quality=100&#038;ssl=1",
    "text": "TRAPRE IE\n31 uf meena o =cbe cane TERY 2000) wi fps. Tate cont (V.,.) oo ar wot\nAT 502 TTT Ga oe wT @d 1-1, orf rege cond way\n2\n( 205 PE ® 1 PY\n200 5 £ Ie\nSs 200 a»\nom pros [L] 208\nSY af while ICTS CTY 2R | SHNTER TE CET > hy\nrele oni rot su em, whrefés av wap 0 Ie le\n® K ® ® 4 4\n(n IR ® =\nso carDiibr «fl Swany afd — >I >\n(3) wifibra @ refit 01 ws wy @ wom wfmve cen pv\n(1) woafrefibre (9) Brrwm ona CEIfrYTS BITTE TE\n361 ow Sr eT WTR WE wg (es fife ® n 1\nRevafiree cm— Y\n® aw (9) cfr (N r+! ( y-!\n® (v) ww R31 Frese cata fiver owen dQ = dW wm?\nse af cele seme mc? mT ToT 9 @ om afi\nwT wr (0) ween\nsrsrren afzF\n® me o oi aff\n0 V3\n™ Wim 31 wi 5 com on wv 78 Tw\n© ® = (0 Fl\n© Bm yd ol\nsor Coe i te oy wel Rag 3910 SOT Coe of pv wo epee\nPRR TE T— 0.03cm Ton ETAT FTE FH?\n-3 4 (rg wee #75 3x10%ms™') ;\n0), 107 see 1G @ 10712 «© 109%;\n(M107 sec ® 10% ® 10H: @ 10MHz\n3 fp Tpa Teel. wi fra om\n(®) 039 ® 0693 Ti fare fern om\n(') 0963 (M1443 Hi, FT ATR FAC\n[Rp bs iti, ga fee sre wre ffs\ni oof RSH bm firvsa coral fer\nii. oof Torys wa ® ei (0) ie iit\nii, fig cov cea wR erties Tw () iieiii @ Liisi\n301 Bm a3 fey olen 9afd oy am Fre rw\nhoi fad nce WGA wear\n®) sii (0) ii sii () afer () afer\n(oN) iii @ iii @® wr (2) TER\nHSC & Admission $%W-SEE"
  },
  {
    "image_url": "https://i0.wp.com/i.postimg.cc/D7tYHDv4/11.jpg?resize=800%2C1131&#038;quality=100&#038;ssl=1",
    "text": "Ll wd 3289/3039\nEAH hw\nny as V9 E13\nBE @r fel a\n1203 10ra Frcvram wager] ot =]\nuae WE\nafea—se\nEE TER. ie\nFr yr wR wen Sw aw oft swe fice ow woe gem we\nao Weces UD Tw) Tf VER SU 3 ow a Pe\nTe awa\nTR Cen aww wf orn WA A\n3 eV (RwaGw ced) femse cow afew wy Bi rT oR SER wr TPT Taye\n® wd (¥) ev wan Say\n® ® fro (3) wort oi\n3 as sTimem 427°C 6 227°C wm e Sessoms tied\n“a ww ww | Yew ree ver (x) renga o Cova\n® 35% (\"0 40%\nMm 460% 5% J x WE WH 307% 23 TS\no£ wy PE wr ox SH few ce ApF AUF\nwere fw sTvr —i\n(®) mm (4) ww pe\n@ “wwe (%) wh bl\nFrost 9G wal 8 © ¢ ww Aor Bow\n«fy Frere fig Tr www WE TOW ad\n400 Pa @ fa ce HroBTx 800 J BPE ew 301 TE EAR PU WHEE WEY\n> FEE 1200 J NOW TW (® 16uF (9 suf\n81 wom wary wfee «fwd ws war @ dw 1 uF\n(®) -800J) @ -400) 31 PT Te Ars of wor\n0 -1003 mo) ® 0047 @® oo)\n@1 frm re Sow So mv wn wn Hod (n cory (9 0001)\nwn rere ww Ew S31 Wm ww fivy orien of arent Seer co\n(®) 1200 ® 800) fa wor BTN (TE WDE WT TINCT\n(on) 400) ® 0) TER re fe FE?\nuf TREE PNT YE YAH TH FE ® 22 [ RS\n(%) 385x10-2CmiN- om wn Lo Red\n(© 9x 10°NC m2 S01 porbonchial-beigbad\n85 x 1012 CN“! m2 ® con ad\n(0 sex 102CN tm 2 N i-\n@ 9x10°NmiC?\nOo 381 wn cm wor wes wp wed of\n® av -\n(9 wh ofeefest team\n(m) mere AE had\n© cow ii. wn me\nvi FEY Com ITE Swe of TEE war Poms ol ses @ eu\no es ao on sii (VRYALY\nHSC & Admission 5-6"
  },
  {
    "image_url": "https://i0.wp.com/i.postimg.cc/k7hKVwms/2.jpg?w=804&#038;quality=100&#038;ssl=1",
    "text": "se GSI awe to oy 33) wags fate wir was mies\n@ x! ff gE wd wre ur ce er\n© NK fi 5 Fe rm cafe ena\no ne! K! fu. TEND] Ty wawtady curs ax ave\n© Kio ral\nfarsy SEE WEPICE Yo © 34 HCH Tg we © Feil\non isi\nE-8v ERY ® iii\n— fore Sirs WPT 23 ¢ Yo AE Bow Me\ni v2 fa2a |. fae wire fom @ ww\n! ofr wz Tow X oY awl (red)\nworn ofr sw aw\n100 WI EES wifmtE—\nLo X-wes vod side\nyu TERT TA (i) 47 TW ITY HY FRG TEE\n(®) 088A lil. Y-47 701 03S Tovah\n@ 114A frsz qawb fir\non) 133A ® ai\n®. 160A © 19\nsa TERY HEE TENA TS WN (I CT ® sii\nwere ce FT omew TA? (%) 4 ii Qi\n@® 2 201 Y= X- Y feon 5 vn cu few 2u ex\n«20 1 fires feo co wTaref ore Tur\n40 @ fons fred\n® 1a (¥) for ofiea\ncow fies\nsvi foAr @ 30 Ca tm Br 2 Es er\n(®%) wETTE™ .\noto frsn Ea me ve:\n® “orm AB\n(V) Rem\nSn cee Gf fn erprfe refer wf y\nfore ave ww we Tu Fm wT —\nfe apr wm com fend\n@) =\n® si 281 Wier TE ween gm Few cow oft?\n@ 5 @ XOoR\n© (¥) XNOR\n20 Drfaebe yew wa w— (') NAND\ni xe feo (®) NOR\ni orev Rove 301 CAT Cow GRO STO\niii, fg fon ! syowe By\nfrsz coms afm (® Ty=06931\nCORAL @ T,=06930\n® [ou ) Ty=1A\n0 ei %\n® iii siif (9) Ty, =10693\nHSC & Admission $%W-SEE"
  },
  {
    "image_url": "https://i0.wp.com/i.postimg.cc/PtDXqD0R/1.jpg?resize=804.999999996%2C1139&#038;quality=100&#038;ssl=1",
    "text": "EL wa 092/030\naft wd\n— wee [TE]\nAIEra QE sew\n[2030 07% Freorams werd] on:\nvse GR\nmse\n_\ngt: megs TAR whe Sarr re fs Sim Ay erm were ER TT A Ae\nSaran 7 wm TT Fo wy wed wD BT | £0 wre WAY | rpm eve ew TS A |\nIE COT eR W/o ove we A\nI chiisdasad wud ub aback v1 Cot owt wou fps WC ren ay\ngels ge i» oe Padlhsiony\n”\nprgusibiia a- (on) Asti, (%) fires uo\n© (m) Se ww © TRG awe BETH TCE 3 © So EC BEE We +\n(¥) Taw @ wo omy BER wor A 8\nr=010 L010\n3 wT TE we aw wm—\n(%) wmfajars av\n@ wom Hv\n() Ieee +\n(®) ww wo\n© we foes frre aes Shep > TEN ge ee ofr wer\nTW, THER AT NYS ATG (S) FF TR— @ 1904A\n@ s-00 (%) S=x (4) 0987A\n™) s=010 (0) s=10 (\") 0493 A\n81 aw ww ofS fea TG Ew x; WTO on\n70g me és wor i soi Ww xh cA\" comibe Bowe TY\na 2 Feafears mem oro ero (Ts Tel\n®; 0) Be ww d\n2m TR aS Spm\na 5 psgetaig\n1 furs colt wv ere wo wnt Le\n®) Pw (%) com mw\n@ ww (%) foe\n31 Cw we wm—\n61 hv art ave wn— IY\n® x! ™ r=\n0K »\n(= Ist [ Ray\n=) 1° he\nP=\na1 Fama conf wow rye clr Ref wear Ek\n® ‘Vv avo ® P=\nJRA STR\nwn Iv r ~2V 331 (101001), &¥ cP 1H FO?\n(¥) (42)y0\n[URL iLL ® ci\n-2v HV (7) (40)\n© —Dpww— ® G2 ae\nHSC & Admission $W-SE bw 2"
  },
  {
    "image_url": "https://i0.wp.com/i.postimg.cc/L9Bmtp9k/2.jpg?resize=804.999999996%2C1139&#038;quality=100&#038;ssl=1",
    "text": "31 five re fT we SORE pss 201 Fd EE (Vg) ae om ames wom\nSeo = Tw FE (1) 08 5 rea cat\n(3) fom\n© Severe fm Wi vi\n(7) aes ffm \\\n(%) Furs oer fae ® RG) .\n381 wove Sen fda 3m — © © 0)\n© fr va, vo\n(9) wms -\n() THRE 5 .\nwa (Vo, OY (50.0\n301 SIO of on Tt EY FT 05 » [A]B]x]\ned ENENKE\nA [oe [1]\ni, wT COT\ncen cores Boor [lo]\n=e ENE\n@ iviii ocr ore A or 3E—\niii\n(V4 ii iii (%) NAND oft®\nfsa SEHD ory 36 © S920 99 Me © ow\n7 IPI =f OTT A © B (3 TRA q, = +2C (%) NOR CHP\nER q, = -2C “RA oe wee |\n. aw wm-oxes Row enn:\nSei Acs welt vor wR  evewy\n(®) 16x10 pica\n(0) 32x10 (1) Raw\n(1) 625x108\n@ 125x100 © strom\n301 DmEfvs Soe ce — faces TofS RAKE 30 © YW aH Tew Me ¢\ni [pinks pal po, Bp Bo\nii ASB om rE A TT os\niil. A © B OTeRwy oh une wag LP nll dpi\nfoes¥ colt Afr TZ\n(isu\n(9 iii 301 FOR om cm (1S wR AS erwin\n@ visi (® PQ\n(%) iii Sif ® osR\nsw Fost Gorm ROMER AC CF DC-CO NS War ® Shi\n(¥) we\n® so BS AMY TEE ROT T—\n(0) wer ® z+ 4\n(W) Geer . ®z\nsai ald contin oom why 1.2% 1 4.8 Fre ot oe\n2 cltwfbs vs wer wom wT 1 a\n2 ae coom wemew 4:5 x 1014 Hz @ (oT\n®73 Tver\n©; oe\n125eV\n[J 2 ® 186ev\n© % ) sesev.\norm HSC & Admission $HW-SEE"
  },
  {
    "image_url": "https://i0.wp.com/i.postimg.cc/sjhHTFNx/1.jpg?resize=804.999999996%2C1138&#038;quality=100&#038;ssl=1",
    "text": "we 3833/00\nwf Ew\n-[OT=]\npo em\nAl\nIE QE so Pr seri\nmae KE on =]\nfs\nre ——\nReade: wewcicye Toff wiv STE SU ofvs Avis fvAitT mg strdere on e=\nfli Saree qa wn wre ww wn rnd Sa 52 | row wee Sor fos se, hos\nria wey |\nATR CIT 1 w/o coven wc\n31 me sfmm ovr con® Her A I —\nds=0 (®) dv-o i ume vay wun om saw\n* dQ 0 dW du arse\nA TERS cw ce whew ober :\nco +m fo wi “\nShe lig 231° © 215° B\n6% 320°F| (m) 160-00° © 28800° A\nofr cw fsa cory i A OB conser oy\n2) La ii B cme weg we\now o pie lil. B cla wa wee whe ns vt\nfess coms er\nJ lim (asia\ni om ww Say og wg an (fT af @) isi @ «mw\nii, es Tas we ww | THE wre we =) isi N) die\nii, feds wees wey via | EA a ow ow\nfron @® rer rift ergs ww on |» | aw dee for wR enya fesandar 20\n(® isi <) i€iii J (oe FER EY TE WERE er\non) iisiii ® i, ii © di @® 4% © 2%\n11 a wd see a 1.8x10%Qm on 1% (©) 05%\n3mm TCT FE M0dE ices Ga 12Q wr sot Em wa fies adm fyves moel Tm\n@ 212x10%m  @ 471x10°m Fem we Cow <RATE—\n(0 188x10'm  (¥) 1-88x10''m (®) \"TE (%) fer ace\nv1 weer We pre TE FTI TE (%) OF TER TR\n®) of cof zf ® wee 25 » re fe aed Ty\n(1) Trewms  (V) miafg 23 4fl evga ows ven ors x ed 7ey\n“q) wprew whi wm fer we cE ews (A) 3 rt rose com core 5a en\ney WE TT Wes Sel WP eR\nares fer # Vv V\n<4 =f N\n1 ee 4 A\n= 0; @) \\_ 5) LL\n¥ fiers 1 0 > g Seat\nwen Set (1) Eta\n»~ vi\n= s Vv N\nog / © § A eo\" |\n— > i\nwre: Een (1) wierd Eger (1) 0 > W EER)\nHSC & Admission $%w-3aE"
  },
  {
    "image_url": "https://i0.wp.com/i.postimg.cc/Y2BnVX53/2.jpg?w=804&#038;quality=100&#038;ssl=1",
    "text": "RIT QTE\n331 fim ABC fe AB = AC = 2BD = 2CD Shi — °C am 27°C wre wr faves aw\nam gym +26 © qc Mel A 9D fim fas HA SEE Aen wzy\nfew THRITE Vj, 9 Vp | ® 857 @®\nA on 2132 ®) 0469\n201\nAN =\nBz Ta’ >%\nfiw comm | v Q\n® w>v @ %<v% kd\nMD =Vo (OW 2Vp=W 5 kd\n61 rid comin liom ay TLS Hy 00 fia soph refs aso wom—\nl 0-693 ® sor (f) SamQ\n* bi 7 0; je= T ) PawQ m PemR\n2 H\nkb BU AL He Xe gn fF X cn fre\nZz 0.693, ove\n® 55 © H ® of (6) wb\n@ wr (%) =r\n381 SUTeAE-wr Pow awry\n( Rep (© ffs BA v\no) fre oRromw B .\nsen Emami. five wuw few Sree fore Tie WADE aR\n@ wr ov Shug @ aE @ Row\non) smffam (7) cm\n201 Serf oy BE TW OTH CEO TR 0FCe\n31 COT TER MC STH ad en 5 wu hadi\n(3) Rwy (2) wry (7) 1 aft worse ww TE\n(¥) cot wo em en cafe we\n@ cfrvdmep (v) audweg BH co ver vm wo wv ee\n391 awn wo ob om DG @aB 75 @ afm ati\n920m Wor TE WoT wo | ww gemew 81 GR wens sm sf zor fio co ary\nQtr con fos Geral ray 4 HE on wf eer nfs wer\n@ V=037C  (Y) V<037C ™ peti 4 np\n® voc (w vs03C jy oe ©\n3¢1 Bm 97 R-fy ow ws ww ow nfs\nSori 263 Ff Tw mE— Fras ox aw wow af fds wo\ni wom LTTE TON | THT CST] A —\nii, cece i ATS em\niii, caf ii. WS om\nPS iif, + Sef dws\n@ i 0 i Fr cont fier\n0) iisiii ® iiivii ® isi @ isi\n. on) wei ® isi\nHSC & Admission $5%-3wE"
  },
  {
    "image_url": "https://i0.wp.com/en.lekhaporabd.net/wp-content/uploads/2026/05/Malaysia-Work-Permit-Visa.webp?resize=310%2C165&amp;quality=100&amp;ssl=1",
    "text": "MALAYSIATE | § == fog\nook car vs | | 2) SE\n@ © 00 caida il\n==-R © Ty"
  },
  {
    "image_url": "https://i0.wp.com/en.lekhaporabd.net/wp-content/uploads/2026/04/Portugal-Work-Permit-Visa.webp?resize=310%2C165&amp;quality=100&amp;ssl=1",
    "text": "———\n= rorTuUcH 3\n7\n\\ WORK PERMIT Ss cus\noe “visa UH\noe OE"
  },
  {
    "image_url": "https://i0.wp.com/en.lekhaporabd.net/wp-content/uploads/2026/04/Germany-Opportunity-Card-Visa-promotion.webp?resize=310%2C165&amp;quality=100&amp;ssl=1",
    "text": "= GERMANY\nbd OPPORTUNITY CARD VISA\n[9\ngo =\n= 9 (\n8. Nn wl (16538"
  },
  {
    "image_url": "https://i0.wp.com/en.lekhaporabd.net/wp-content/uploads/2026/04/Australia-Work-Permit-Visa.webp?resize=310%2C165&amp;quality=100&amp;ssl=1",
    "text": "oe"
  },
  {
    "image_url": "https://i0.wp.com/en.lekhaporabd.net/wp-content/uploads/2026/04/Italy-work-permit-visa-guide.webp?resize=310%2C165&amp;quality=100&amp;ssl=1",
    "text": "- BS ITALY Bogs\na WORK PERMIT VISA APPL)\npa Sin Ji corrirecune _\nLd Pr\n48 Thee vais a\n\\ Le FT\nfom Ty"
  }
]