[
  {
    "id": "physics-ssc-science-physics-board-questions-year-wise-2023-dhaka-ts-0",
    "subject": "physics",
    "chapter": "Dhaka Board 2023",
    "text": "গাড়ির সর্বোচ্চ গতিশক্তি কত?",
    "options": [
      "2 × 10⁴ J",
      "4 × 10⁴ J",
      "8 × 10⁵ J",
      "16 × 10⁷ J"
    ],
    "image": null,
    "optionImages": null,
    "timeLimit": 45
  },
  {
    "id": "physics-ssc-science-physics-board-questions-year-wise-2023-dhaka-ts-1",
    "subject": "physics",
    "chapter": "Dhaka Board 2023",
    "text": "গাড়িটি-\ni. 2 m/s² ত্বরণে যাত্রা শুরু করে\nii. থামার পূর্বে গাড়িটির মন্দন 1 m/s²\niii. সমবেগে 1200 m পথ অতিক্রম করে\nনিচের কোনটি সঠিক?",
    "options": [
      "i ও ii",
      "i ও iii",
      "ii ও iii",
      "i, ii ও iii"
    ],
    "image": null,
    "optionImages": null,
    "timeLimit": 45
  },
  {
    "id": "physics-ssc-science-physics-board-questions-year-wise-2023-dhaka-ts-2",
    "subject": "physics",
    "chapter": "Dhaka Board 2023",
    "text": "বর্তনীতে কী পরিমাণ তড়িৎ প্রবাহিত হচ্ছে?\n[R₁ = 6Ω, R₂ = 4Ω, R₃ = 2Ω, EMF = 6V]",
    "options": [
      "0.5 A",
      "2 A",
      "5.5 A",
      "72 A"
    ],
    "image": "/images/quiz/cell-terminal-pd.svg",
    "optionImages": null,
    "timeLimit": 45
  },
  {
    "id": "physics-ssc-science-physics-board-questions-year-wise-2023-dhaka-ts-3",
    "subject": "physics",
    "chapter": "Dhaka Board 2023",
    "text": "সকলটি রোধকে সমান্তরালে সাজালে তুল্য রোধ 'Rp' কেমন হবে?\n[R₁ = 6Ω, R₂ = 4Ω, R₃ = 2Ω]",
    "options": [
      "Rp < R₂ কিন্তু Rp > R₃",
      "Rp < R₁ কিন্তু Rp > R₂",
      "Rp < R₂ এবং Rp = R₃",
      "Rp < R₂ এবং Rp > R₃"
    ],
    "image": null,
    "optionImages": null,
    "timeLimit": 45
  },
  {
    "id": "physics-ssc-science-physics-board-questions-year-wise-2023-dhaka-ts-4",
    "subject": "physics",
    "chapter": "Dhaka Board 2023",
    "text": "একটি উত্তল আয়নার বক্রতার ব্যাসার্ধ 6cm। আয়নার 2cm সামনে একটি লক্ষ্যবস্তু রাখলে এর প্রতিবিম্ব হবে-\ni. অবাস্তব ও সোজা\nii. বাস্তব ও উল্টো\niii. তিনগুণ বর্ধিত\nনিচের কোনটি সঠিক?",
    "options": [
      "i ও ii",
      "i ও iii",
      "ii ও iii",
      "i, ii ও iii"
    ],
    "image": null,
    "optionImages": null,
    "timeLimit": 45
  },
  {
    "id": "physics-ssc-science-physics-board-questions-year-wise-2023-dhaka-ts-5",
    "subject": "physics",
    "chapter": "Dhaka Board 2023",
    "text": "একটি শব্দতরঙ্গ বাতাসে 5s এ 1750m পথ অতিক্রম করে। তরঙ্গটির তরঙ্গ দৈর্ঘ্য 0.5m হলে কম্পাঙ্ক কত?",
    "options": [
      "0.00143 Hz",
      "175 Hz",
      "700 Hz",
      "3500 Hz"
    ],
    "image": null,
    "optionImages": null,
    "timeLimit": 45
  },
  {
    "id": "physics-ssc-science-physics-board-questions-year-wise-2023-dhaka-ts-6",
    "subject": "physics",
    "chapter": "Dhaka Board 2023",
    "text": "1 cc কেরোসিনের ভর 0.8g। কেরোসিনের 50 cm গভীরে চাপ কত?",
    "options": [
      "392000 Nm⁻²",
      "3920 Nm⁻²",
      "392 Nm⁻²",
      "3.92 Nm⁻²"
    ],
    "image": null,
    "optionImages": null,
    "timeLimit": 45
  },
  {
    "id": "physics-ssc-science-physics-board-questions-year-wise-2023-dhaka-ts-7",
    "subject": "physics",
    "chapter": "Dhaka Board 2023",
    "text": "একটি ঢালু তলের উপর দিয়ে একটি ক্রিকেট বল গড়িয়ে পড়লে কোন ধরনের ঘর্ষণ সৃষ্টি হয়?",
    "options": [
      "স্থিতি ঘর্ষণ",
      "গতি ঘর্ষণ",
      "আবর্ত ঘর্ষণ",
      "প্রবাহী ঘর্ষণ"
    ],
    "image": null,
    "optionImages": null,
    "timeLimit": 45
  },
  {
    "id": "physics-ssc-science-physics-board-questions-year-wise-2023-dhaka-ts-8",
    "subject": "physics",
    "chapter": "Dhaka Board 2023",
    "text": "'হাতে হাতে ঘষলে তাপ উৎপন্ন হয়'। এটি শক্তির কী ধরনের রূপান্তর?",
    "options": [
      "রাসায়নিক শক্তি থেকে তাপ শক্তি",
      "তড়িৎ শক্তি থেকে তাপ শক্তি",
      "তাপ শক্তি থেকে যান্ত্রিক শক্তি",
      "যান্ত্রিক শক্তি থেকে তাপ শক্তি"
    ],
    "image": null,
    "optionImages": null,
    "timeLimit": 45
  },
  {
    "id": "physics-ssc-science-physics-board-questions-year-wise-2023-dhaka-ts-9",
    "subject": "physics",
    "chapter": "Dhaka Board 2023",
    "text": "নিচের কোন পদার্থের ইয়ং মডুলাস সবচেয়ে কম?",
    "options": [
      "কাঠ",
      "কাঁচ",
      "তামা",
      "হীরা"
    ],
    "image": null,
    "optionImages": null,
    "timeLimit": 45
  },
  {
    "id": "physics-ssc-science-physics-board-questions-year-wise-2023-dhaka-ts-10",
    "subject": "physics",
    "chapter": "Dhaka Board 2023",
    "text": "নিচের কোন মাধ্যমে শব্দ সবচেয়ে দ্রুত চলে?",
    "options": [
      "হাইড্রোজেন",
      "লোহা",
      "পারদ",
      "পানি"
    ],
    "image": null,
    "optionImages": null,
    "timeLimit": 45
  },
  {
    "id": "physics-ssc-science-physics-board-questions-year-wise-2023-dhaka-ts-11",
    "subject": "physics",
    "chapter": "Dhaka Board 2023",
    "text": "অবতল আয়নার-\ni. ফোকাস দূরত্ব, বক্রতার ব্যাসার্ধের অর্ধেক\nii. ফোকাস দূরত্ব অসীম হলে, সেটি সমতল আয়না হবে\niii. মেরু ও প্রধান ফোকাসের মাঝে কোনো বস্তু রাখলে তার প্রতিবিম্ব অবাস্তব হবে\nনিচের কোনটি সঠিক?",
    "options": [
      "i ও ii",
      "i ও iii",
      "ii ও iii",
      "i, ii ও iii"
    ],
    "image": null,
    "optionImages": null,
    "timeLimit": 45
  },
  {
    "id": "physics-ssc-science-physics-board-questions-year-wise-2023-dhaka-ts-12",
    "subject": "physics",
    "chapter": "Dhaka Board 2023",
    "text": "নিচের কোন পদার্থটি সর্বাধিক বিদ্যুৎ পরিবাহী?",
    "options": [
      "সোনা",
      "তামা",
      "রূপা",
      "গ্রাফাইট"
    ],
    "image": null,
    "optionImages": null,
    "timeLimit": 45
  },
  {
    "id": "physics-ssc-science-physics-board-questions-year-wise-2023-dhaka-ts-13",
    "subject": "physics",
    "chapter": "Dhaka Board 2023",
    "text": "লোহার ঘনত্ব কত?",
    "options": [
      "7.80 gm/cc",
      "2.60 gm/cc",
      "1.00 gm/cc",
      "0.25 gm/cc"
    ],
    "image": null,
    "optionImages": null,
    "timeLimit": 45
  },
  {
    "id": "physics-ssc-science-physics-board-questions-year-wise-2023-dhaka-ts-14",
    "subject": "physics",
    "chapter": "Dhaka Board 2023",
    "text": "শব্দের তীব্রতার একক হচ্ছে-",
    "options": [
      "Hz",
      "dB",
      "Wm⁻²",
      "W·Hz"
    ],
    "image": null,
    "optionImages": null,
    "timeLimit": 45
  },
  {
    "id": "physics-ssc-science-physics-board-questions-year-wise-2023-dhaka-ts-15",
    "subject": "physics",
    "chapter": "Dhaka Board 2023",
    "text": "তরঙ্গ দৈর্ঘ্য যদি দৃশ্যমান আলোর সর্বোচ্চ তরঙ্গ দৈর্ঘ্যের চেয়েও বড় হয়, সেটাকে আমরা কী বলি?",
    "options": [
      "আল্ট্রাভায়োলেট",
      "এক্স-রে",
      "গামা-রে",
      "ইনফ্রারেড"
    ],
    "image": null,
    "optionImages": null,
    "timeLimit": 45
  },
  {
    "id": "physics-ssc-science-physics-board-questions-year-wise-2023-dhaka-ts-16",
    "subject": "physics",
    "chapter": "Dhaka Board 2023",
    "text": "কোনো পরিবাহীর মধ্য দিয়ে t সময়ে যদি Q চার্জ প্রবাহিত হয় তবে তড়িৎ প্রবাহ হবে-",
    "options": [
      "I = Q/t",
      "I = t/Q",
      "I = Qt",
      "I = Q²t"
    ],
    "image": null,
    "optionImages": null,
    "timeLimit": 45
  },
  {
    "id": "physics-ssc-science-physics-board-questions-year-wise-2023-dhaka-ts-17",
    "subject": "physics",
    "chapter": "Dhaka Board 2023",
    "text": "1 গিগাবাইট হলো-\ni. 1 মেগাবাইটের 1000 গুণ বড়\nii. 1 টেরাবাইটের 1000 গুণ ছোট\niii. 1 কিলোবাইটের 10⁹ গুণ বড়\nনিচের কোনটি সঠিক?",
    "options": [
      "iii",
      "i ও ii",
      "i ও iii",
      "i, ii ও iii"
    ],
    "image": null,
    "optionImages": null,
    "timeLimit": 45
  },
  {
    "id": "physics-ssc-science-physics-board-questions-year-wise-2023-dhaka-ts-18",
    "subject": "physics",
    "chapter": "Dhaka Board 2023",
    "text": "স্থির অবস্থান থেকে সুষম ত্বরণে চলমান কোনো বস্তুর বেগ-",
    "options": [
      "সময়ের বর্গমূলের সমানুপাতিক",
      "সরণের বর্গমূলের সমানুপাতিক",
      "সময়ের বর্গের সমানুপাতিক",
      "সরণের বর্গের সমানুপাতিক"
    ],
    "image": null,
    "optionImages": null,
    "timeLimit": 45
  },
  {
    "id": "physics-ssc-science-physics-board-questions-year-wise-2023-dhaka-ts-19",
    "subject": "physics",
    "chapter": "Dhaka Board 2023",
    "text": "কে প্রথম কার্যকারণ ও যুক্তি ছাড়া শুধু ধর্ম অতীন্দ্রিয় ও পৌরাণিক কাহিনিভিত্তিক ব্যাখ্যা গ্রহণ করতে অস্বীকার করেছিলেন?",
    "options": [
      "থেলিস",
      "পিথাগোরাস",
      "ডেমোক্রিটাস",
      "আরিস্টটল"
    ],
    "image": null,
    "optionImages": null,
    "timeLimit": 45
  },
  {
    "id": "physics-ssc-science-physics-board-questions-year-wise-2023-dhaka-ts-20",
    "subject": "physics",
    "chapter": "Dhaka Board 2023",
    "text": "প্রোটনের ব্যাসার্ধ কত?",
    "options": [
      "7 × 10⁻⁷ m",
      "5 × 10⁻¹¹ m",
      "1 × 10⁻¹⁵ m",
      "9 × 10³¹ m"
    ],
    "image": null,
    "optionImages": null,
    "timeLimit": 45
  },
  {
    "id": "physics-ssc-science-physics-board-questions-year-wise-2023-dhaka-ts-21",
    "subject": "physics",
    "chapter": "Dhaka Board 2023",
    "text": "বেগের মাত্রা কোনটি?",
    "options": [
      "LT⁻²",
      "L²T",
      "L⁻¹T",
      "LT⁻¹"
    ],
    "image": null,
    "optionImages": null,
    "timeLimit": 45
  },
  {
    "id": "physics-ssc-science-physics-board-questions-year-wise-2023-dhaka-ts-22",
    "subject": "physics",
    "chapter": "Dhaka Board 2023",
    "text": "সূর্য থেকে আলো ও তাপ তৈরি হয় কোন বল দিয়ে?",
    "options": [
      "মহাকর্ষ বল",
      "বিদ্যুৎ চৌম্বকীয় বল",
      "দুর্বল নিউক্লিয় বল",
      "সবল নিউক্লিয় বল"
    ],
    "image": null,
    "optionImages": null,
    "timeLimit": 45
  },
  {
    "id": "physics-ssc-science-physics-board-questions-year-wise-2023-dhaka-ts-23",
    "subject": "physics",
    "chapter": "Dhaka Board 2023",
    "text": "বস্তুর ভরবেগের পরিবর্তনের হার তার উপর প্রযুক্ত বলের-",
    "options": [
      "ব্যস্তানুপাতিক",
      "বর্গের সমানুপাতিক",
      "সমানুপাতিক",
      "বর্গের ব্যস্তানুপাতিক"
    ],
    "image": null,
    "optionImages": null,
    "timeLimit": 45
  },
  {
    "id": "physics-ssc-science-physics-board-questions-year-wise-2023-dhaka-ts-24",
    "subject": "physics",
    "chapter": "Dhaka Board 2023",
    "text": "প্রকৃতিতে ইউরেনিয়ামের পরিমাণ কত?",
    "options": [
      "0.07%",
      "0.7%",
      "7%",
      "7.7%"
    ],
    "image": null,
    "optionImages": null,
    "timeLimit": 45
  }
]
