{
  "hsc-biology-1st-paper-chapter-11-set-08-q01": {
    "correctOption": "রোগ/পোকা প্রতিরোধ",
    "explanation": "Transgenic crops may be resistant."
  },
  "hsc-biology-1st-paper-chapter-11-set-08-q02": {
    "correctOption": "বিদেশি জিন বহন করতে পারে",
    "explanation": "Plasmid carries foreign gene."
  },
  "hsc-biology-1st-paper-chapter-11-set-08-q03": {
    "correctOption": "ট্রান্সজেনিক উদ্ভিদ",
    "explanation": "Transgenic plant carries foreign gene."
  },
  "hsc-biology-1st-paper-chapter-11-set-08-q04": {
    "correctOption": "Shoot apical meristem",
    "explanation": "Meristem culture produces virus-free plant."
  },
  "hsc-biology-1st-paper-chapter-11-set-08-q05": {
    "correctOption": "DNA ligase",
    "explanation": "Ligase joins DNA fragments."
  },
  "hsc-biology-1st-paper-chapter-11-set-08-q06": {
    "correctOption": "restriction enzyme, ligase ও vector",
    "explanation": "Core tools of rDNA."
  },
  "hsc-biology-1st-paper-chapter-11-set-08-q07": {
    "correctOption": "E. coli",
    "explanation": "E. coli used as host."
  },
  "hsc-biology-1st-paper-chapter-11-set-08-q08": {
    "correctOption": "রেস্ট্রিকশন এন্ডোনিউক্লিয়েজ",
    "explanation": "Restriction enzyme molecular scissors."
  },
  "hsc-biology-1st-paper-chapter-11-set-08-q09": {
    "correctOption": "Kary Mullis",
    "explanation": "Kary Mullis invented PCR."
  },
  "hsc-biology-1st-paper-chapter-11-set-08-q10": {
    "correctOption": "Polymerase Chain Reaction",
    "explanation": "PCR amplifies DNA."
  },
  "hsc-biology-1st-paper-chapter-11-set-08-q11": {
    "correctOption": "অ্যান্টিবায়োটিক প্রতিরোধী জিন",
    "explanation": "R-plasmid has resistance gene."
  },
  "hsc-biology-1st-paper-chapter-11-set-08-q12": {
    "correctOption": "লক্ষ্য DNA আলাদা করা",
    "explanation": "Target DNA isolation."
  },
  "hsc-biology-1st-paper-chapter-11-set-08-q13": {
    "correctOption": "DNA বেসের ক্রম",
    "explanation": "Sequencing reveals base order."
  },
  "hsc-biology-1st-paper-chapter-11-set-08-q14": {
    "correctOption": "DNA খণ্ড",
    "explanation": "Gel electrophoresis separates DNA fragments."
  },
  "hsc-biology-1st-paper-chapter-11-set-08-q15": {
    "correctOption": "এক্সপ্লান্ট",
    "explanation": "Explant is plant tissue used."
  },
  "hsc-biology-1st-paper-chapter-11-set-08-q16": {
    "correctOption": "রোগ/পোকা প্রতিরোধ",
    "explanation": "Transgenic crops may be resistant."
  },
  "hsc-biology-1st-paper-chapter-11-set-08-q17": {
    "correctOption": "বিদেশি জিন বহন করতে পারে",
    "explanation": "Plasmid carries foreign gene."
  },
  "hsc-biology-1st-paper-chapter-11-set-08-q18": {
    "correctOption": "ট্রান্সজেনিক উদ্ভিদ",
    "explanation": "Transgenic plant carries foreign gene."
  },
  "hsc-biology-1st-paper-chapter-11-set-08-q19": {
    "correctOption": "Shoot apical meristem",
    "explanation": "Meristem culture produces virus-free plant."
  },
  "hsc-biology-1st-paper-chapter-11-set-08-q20": {
    "correctOption": "DNA ligase",
    "explanation": "Ligase joins DNA fragments."
  },
  "hsc-biology-1st-paper-chapter-11-set-08-q21": {
    "correctOption": "restriction enzyme, ligase ও vector",
    "explanation": "Core tools of rDNA."
  },
  "hsc-biology-1st-paper-chapter-11-set-08-q22": {
    "correctOption": "E. coli",
    "explanation": "E. coli used as host."
  },
  "hsc-biology-1st-paper-chapter-11-set-08-q23": {
    "correctOption": "Kary Mullis",
    "explanation": "Kary Mullis invented PCR."
  },
  "hsc-biology-1st-paper-chapter-11-set-08-q24": {
    "correctOption": "Taq polymerase",
    "explanation": "Taq polymerase heat-stable DNA polymerase। — HSC Biology 1st Paper বোর্ড-স্ট্যান্ডার্ড ও repeated concept ভিত্তিক গুরুত্বপূর্ণ MCQ।"
  },
  "hsc-biology-1st-paper-chapter-11-set-08-q25": {
    "correctOption": "Polymerase Chain Reaction",
    "explanation": "PCR amplifies DNA."
  }
}
