{
  "hsc-biology-1st-paper-chapter-10-set-01-q01": {
    "correctOption": "i, ii ও iii",
    "explanation": ""
  },
  "hsc-biology-1st-paper-chapter-10-set-01-q02": {
    "correctOption": "i ও ii",
    "explanation": ""
  },
  "hsc-biology-1st-paper-chapter-10-set-01-q03": {
    "correctOption": "i, ii ও iii",
    "explanation": ""
  },
  "hsc-biology-1st-paper-chapter-10-set-01-q04": {
    "correctOption": "i, ii ও iii",
    "explanation": ""
  },
  "hsc-biology-1st-paper-chapter-10-set-01-q05": {
    "correctOption": "কুমড়া",
    "explanation": ""
  },
  "hsc-biology-1st-paper-chapter-10-set-01-q06": {
    "correctOption": "ওপেন",
    "explanation": ""
  },
  "hsc-biology-1st-paper-chapter-10-set-01-q07": {
    "correctOption": "টুইস্টেড",
    "explanation": ""
  },
  "hsc-biology-1st-paper-chapter-10-set-01-q08": {
    "correctOption": "৬",
    "explanation": "বোর্ড-স্ট্যান্ডার্ড কনসেপ্ট অনুযায়ী সঠিক উত্তরটি নির্বাচিত। — 2023 সালের board-question pattern থেকে নেওয়া/রূপান্তরিত high-priority MCQ।"
  },
  "hsc-biology-1st-paper-chapter-10-set-01-q09": {
    "correctOption": "নিষেক",
    "explanation": "Fusion of gametes is fertilization। — HSC Biology 1st Paper বোর্ড-স্ট্যান্ডার্ড ও repeated concept ভিত্তিক গুরুত্বপূর্ণ MCQ।"
  },
  "hsc-biology-1st-paper-chapter-10-set-01-q10": {
    "correctOption": "বৃক্কাকার বা এক প্রকোষ্ঠবিশিষ্ট (Kidney-shaped)",
    "explanation": "বৃক্কাকার বা এক প্রকোষ্ঠবিশিষ্ট। — HSC Biology 1st Paper বোর্ড-স্ট্যান্ডার্ড ও repeated concept ভিত্তিক গুরুত্বপূর্ণ MCQ।"
  },
  "hsc-biology-1st-paper-chapter-10-set-01-q11": {
    "correctOption": "পরাগধানীতে (Anther)",
    "explanation": "পরাগধানীতে। — HSC Biology 1st Paper বোর্ড-স্ট্যান্ডার্ড ও repeated concept ভিত্তিক গুরুত্বপূর্ণ MCQ।"
  },
  "hsc-biology-1st-paper-chapter-10-set-01-q12": {
    "correctOption": "ভ্রূণ",
    "explanation": "Zygote develops into embryo। — HSC Biology 1st Paper বোর্ড-স্ট্যান্ডার্ড ও repeated concept ভিত্তিক গুরুত্বপূর্ণ MCQ।"
  },
  "hsc-biology-1st-paper-chapter-10-set-01-q13": {
    "correctOption": "উজ্জ্বল রং ও মধু",
    "explanation": "Insect-pollinated flowers colorful and nectar-bearing। — HSC Biology 1st Paper বোর্ড-স্ট্যান্ডার্ড ও repeated concept ভিত্তিক গুরুত্বপূর্ণ MCQ।"
  },
  "hsc-biology-1st-paper-chapter-10-set-01-q14": {
    "correctOption": "স্বপরাগায়ন",
    "explanation": "Self pollination occurs within same flower/plant। — HSC Biology 1st Paper বোর্ড-স্ট্যান্ডার্ড ও repeated concept ভিত্তিক গুরুত্বপূর্ণ MCQ।"
  },
  "hsc-biology-1st-paper-chapter-10-set-01-q15": {
    "correctOption": "হালকা ও অসংখ্য",
    "explanation": "Wind-pollinated pollen light and numerous। — HSC Biology 1st Paper বোর্ড-স্ট্যান্ডার্ড ও repeated concept ভিত্তিক গুরুত্বপূর্ণ MCQ।"
  },
  "hsc-biology-1st-paper-chapter-10-set-01-q16": {
    "correctOption": "ফল, বীজ",
    "explanation": "ফুল গর্ভাশয়ের প্রভাবে ফল, আর ডিম্বকটি পরিণত হয়ে বীজে রূপান্তরিত হয়। — HSC Biology 1st Paper বোর্ড-স্ট্যান্ডার্ড ও repeated concept ভিত্তিক গুরুত্বপূর্ণ MCQ।"
  },
  "hsc-biology-1st-paper-chapter-10-set-01-q17": {
    "correctOption": "৬টি",
    "explanation": "৬টি। (লজিক: এটি একবীজপত্রীর সাধারণ থ্রি-ফোল্ড সূত্রের ব্যতিক্রম, যা একে পোয়াসির শক্তিশালী শনাক্তকারী বানায়)। — HSC Biology 1st Paper বোর্ড-স্ট্যান্ডার্ড ও repeated concept ভিত্তিক গুরুত্বপূর্ণ MCQ।"
  },
  "hsc-biology-1st-paper-chapter-10-set-01-q18": {
    "correctOption": "ফল",
    "explanation": "Ovary develops into fruit। — HSC Biology 1st Paper বোর্ড-স্ট্যান্ডার্ড ও repeated concept ভিত্তিক গুরুত্বপূর্ণ MCQ।"
  },
  "hsc-biology-1st-paper-chapter-10-set-01-q19": {
    "correctOption": "এম্ব্রিও স্যাক",
    "explanation": "Embryo sac is female gametophyte of angiosperm। — HSC Biology 1st Paper বোর্ড-স্ট্যান্ডার্ড ও repeated concept ভিত্তিক গুরুত্বপূর্ণ MCQ।"
  },
  "hsc-biology-1st-paper-chapter-10-set-01-q20": {
    "correctOption": "মালভেসি (Malvaceae)",
    "explanation": "মালভেসি। — HSC Biology 1st Paper বোর্ড-স্ট্যান্ডার্ড ও repeated concept ভিত্তিক গুরুত্বপূর্ণ MCQ।"
  },
  "hsc-biology-1st-paper-chapter-10-set-01-q21": {
    "correctOption": "পরাগরেণু",
    "explanation": "Pollen grain germinates forming pollen tube। — HSC Biology 1st Paper বোর্ড-স্ট্যান্ডার্ড ও repeated concept ভিত্তিক গুরুত্বপূর্ণ MCQ।"
  },
  "hsc-biology-1st-paper-chapter-10-set-01-q22": {
    "correctOption": "পরাগধানীতে",
    "explanation": "Microspore forms in anther। — HSC Biology 1st Paper বোর্ড-স্ট্যান্ডার্ড ও repeated concept ভিত্তিক গুরুত্বপূর্ণ MCQ।"
  },
  "hsc-biology-1st-paper-chapter-10-set-01-q23": {
    "correctOption": "অ্যাপোমিক্সিস",
    "explanation": "Apomixis seed formation without fertilization। — HSC Biology 1st Paper বোর্ড-স্ট্যান্ডার্ড ও repeated concept ভিত্তিক গুরুত্বপূর্ণ MCQ।"
  },
  "hsc-biology-1st-paper-chapter-10-set-01-q24": {
    "correctOption": "কন্দ",
    "explanation": "Potato tuber vegetative propagation। — HSC Biology 1st Paper বোর্ড-স্ট্যান্ডার্ড ও repeated concept ভিত্তিক গুরুত্বপূর্ণ MCQ।"
  },
  "hsc-biology-1st-paper-chapter-10-set-01-q25": {
    "correctOption": "ডিম্বকে",
    "explanation": "Megaspore develops in ovule। — HSC Biology 1st Paper বোর্ড-স্ট্যান্ডার্ড ও repeated concept ভিত্তিক গুরুত্বপূর্ণ MCQ।"
  }
}
