[
  {
    "question_id": "hsc-physics_2ndpaper-chapter-01-set-01-q01",
    "status": "svg_missing",
    "detected_type": "physics_graph",
    "priority": "high"
  },
  {
    "question_id": "hsc-physics_2ndpaper-chapter-01-set-02-q21",
    "status": "svg_missing",
    "detected_type": "physics_graph",
    "priority": "high"
  },
  {
    "question_id": "hsc-physics_2ndpaper-chapter-01-set-03-q14",
    "status": "svg_missing",
    "detected_type": "physics_graph",
    "priority": "high"
  },
  {
    "question_id": "hsc-physics_2ndpaper-chapter-01-set-04-q07",
    "status": "svg_missing",
    "detected_type": "physics_graph",
    "priority": "high"
  },
  {
    "question_id": "hsc-physics_2ndpaper-chapter-01-set-06-q20",
    "status": "svg_missing",
    "detected_type": "physics_graph",
    "priority": "high"
  },
  {
    "question_id": "hsc-physics_2ndpaper-chapter-01-set-07-q13",
    "status": "svg_missing",
    "detected_type": "physics_graph",
    "priority": "high"
  },
  {
    "question_id": "hsc-physics_2ndpaper-chapter-01-set-08-q06",
    "status": "svg_missing",
    "detected_type": "physics_graph",
    "priority": "high"
  },
  {
    "question_id": "hsc-physics_2ndpaper-chapter-01-set-10-q19",
    "status": "svg_missing",
    "detected_type": "physics_graph",
    "priority": "high"
  },
  {
    "question_id": "hsc-physics_2ndpaper-chapter-02-set-01-q05",
    "status": "svg_missing",
    "detected_type": "physics_graph",
    "priority": "high"
  },
  {
    "question_id": "hsc-physics_2ndpaper-chapter-02-set-01-q20",
    "status": "svg_missing",
    "detected_type": "physics_graph",
    "priority": "high"
  },
  {
    "question_id": "hsc-physics_2ndpaper-chapter-02-set-02-q17",
    "status": "svg_missing",
    "detected_type": "physics_graph",
    "priority": "high"
  },
  {
    "question_id": "hsc-physics_2ndpaper-chapter-02-set-03-q10",
    "status": "svg_missing",
    "detected_type": "physics_graph",
    "priority": "high"
  },
  {
    "question_id": "hsc-physics_2ndpaper-chapter-02-set-04-q03",
    "status": "svg_missing",
    "detected_type": "physics_graph",
    "priority": "high"
  },
  {
    "question_id": "hsc-physics_2ndpaper-chapter-02-set-04-q23",
    "status": "svg_missing",
    "detected_type": "physics_graph",
    "priority": "high"
  },
  {
    "question_id": "hsc-physics_2ndpaper-chapter-02-set-05-q15",
    "status": "svg_missing",
    "detected_type": "physics_graph",
    "priority": "high"
  },
  {
    "question_id": "hsc-physics_2ndpaper-chapter-02-set-06-q08",
    "status": "svg_missing",
    "detected_type": "physics_graph",
    "priority": "high"
  },
  {
    "question_id": "hsc-physics_2ndpaper-chapter-02-set-07-q01",
    "status": "svg_missing",
    "detected_type": "physics_graph",
    "priority": "high"
  },
  {
    "question_id": "hsc-physics_2ndpaper-chapter-02-set-08-q13",
    "status": "svg_missing",
    "detected_type": "physics_graph",
    "priority": "high"
  },
  {
    "question_id": "hsc-physics_2ndpaper-chapter-02-set-09-q06",
    "status": "svg_missing",
    "detected_type": "physics_graph",
    "priority": "high"
  },
  {
    "question_id": "hsc-physics_2ndpaper-chapter-02-set-10-q18",
    "status": "svg_missing",
    "detected_type": "physics_graph",
    "priority": "high"
  },
  {
    "question_id": "hsc-physics_2ndpaper-chapter-03-set-02-q20",
    "status": "svg_missing",
    "detected_type": "physics_graph",
    "priority": "high"
  },
  {
    "question_id": "hsc-physics_2ndpaper-chapter-03-set-03-q13",
    "status": "svg_missing",
    "detected_type": "physics_graph",
    "priority": "high"
  },
  {
    "question_id": "hsc-physics_2ndpaper-chapter-03-set-04-q06",
    "status": "svg_missing",
    "detected_type": "physics_graph",
    "priority": "high"
  },
  {
    "question_id": "hsc-physics_2ndpaper-chapter-03-set-07-q21",
    "status": "svg_missing",
    "detected_type": "physics_graph",
    "priority": "high"
  },
  {
    "question_id": "hsc-physics_2ndpaper-chapter-03-set-08-q14",
    "status": "svg_missing",
    "detected_type": "physics_graph",
    "priority": "high"
  },
  {
    "question_id": "hsc-physics_2ndpaper-chapter-03-set-09-q07",
    "status": "svg_missing",
    "detected_type": "physics_graph",
    "priority": "high"
  },
  {
    "question_id": "hsc-physics_2ndpaper-chapter-04-set-01-q07",
    "status": "svg_missing",
    "detected_type": "physics_graph",
    "priority": "high"
  },
  {
    "question_id": "hsc-physics_2ndpaper-chapter-04-set-02-q19",
    "status": "svg_missing",
    "detected_type": "physics_graph",
    "priority": "high"
  },
  {
    "question_id": "hsc-physics_2ndpaper-chapter-04-set-03-q08",
    "status": "svg_missing",
    "detected_type": "physics_graph",
    "priority": "high"
  },
  {
    "question_id": "hsc-physics_2ndpaper-chapter-04-set-03-q21",
    "status": "svg_missing",
    "detected_type": "physics_graph",
    "priority": "high"
  },
  {
    "question_id": "hsc-physics_2ndpaper-chapter-04-set-04-q10",
    "status": "svg_missing",
    "detected_type": "physics_graph",
    "priority": "high"
  },
  {
    "question_id": "hsc-physics_2ndpaper-chapter-04-set-07-q23",
    "status": "svg_missing",
    "detected_type": "physics_graph",
    "priority": "high"
  },
  {
    "question_id": "hsc-physics_2ndpaper-chapter-04-set-08-q12",
    "status": "svg_missing",
    "detected_type": "physics_graph",
    "priority": "high"
  },
  {
    "question_id": "hsc-physics_2ndpaper-chapter-04-set-08-q23",
    "status": "svg_missing",
    "detected_type": "physics_graph",
    "priority": "high"
  },
  {
    "question_id": "hsc-physics_2ndpaper-chapter-04-set-08-q24",
    "status": "svg_missing",
    "detected_type": "physics_graph",
    "priority": "high"
  },
  {
    "question_id": "hsc-physics_2ndpaper-chapter-04-set-09-q12",
    "status": "svg_missing",
    "detected_type": "physics_graph",
    "priority": "high"
  },
  {
    "question_id": "hsc-physics_2ndpaper-chapter-04-set-09-q13",
    "status": "svg_missing",
    "detected_type": "physics_graph",
    "priority": "high"
  },
  {
    "question_id": "hsc-physics_2ndpaper-chapter-04-set-10-q21",
    "status": "svg_missing",
    "detected_type": "physics_graph",
    "priority": "high"
  },
  {
    "question_id": "hsc-physics_2ndpaper-chapter-04-set-10-q23",
    "status": "svg_missing",
    "detected_type": "physics_graph",
    "priority": "high"
  },
  {
    "question_id": "hsc-physics_2ndpaper-chapter-05-set-01-q04",
    "status": "svg_missing",
    "detected_type": "physics_graph",
    "priority": "high"
  },
  {
    "question_id": "hsc-physics_2ndpaper-chapter-05-set-01-q10",
    "status": "svg_missing",
    "detected_type": "physics_graph",
    "priority": "high"
  },
  {
    "question_id": "hsc-physics_2ndpaper-chapter-05-set-02-q05",
    "status": "svg_missing",
    "detected_type": "physics_graph",
    "priority": "high"
  },
  {
    "question_id": "hsc-physics_2ndpaper-chapter-05-set-02-q22",
    "status": "svg_missing",
    "detected_type": "physics_graph",
    "priority": "high"
  },
  {
    "question_id": "hsc-physics_2ndpaper-chapter-05-set-03-q06",
    "status": "svg_missing",
    "detected_type": "physics_graph",
    "priority": "high"
  },
  {
    "question_id": "hsc-physics_2ndpaper-chapter-05-set-03-q11",
    "status": "svg_missing",
    "detected_type": "physics_graph",
    "priority": "high"
  },
  {
    "question_id": "hsc-physics_2ndpaper-chapter-05-set-03-q24",
    "status": "svg_missing",
    "detected_type": "physics_graph",
    "priority": "high"
  },
  {
    "question_id": "hsc-physics_2ndpaper-chapter-05-set-04-q07",
    "status": "svg_missing",
    "detected_type": "physics_graph",
    "priority": "high"
  },
  {
    "question_id": "hsc-physics_2ndpaper-chapter-05-set-04-q13",
    "status": "svg_missing",
    "detected_type": "physics_graph",
    "priority": "high"
  },
  {
    "question_id": "hsc-physics_2ndpaper-chapter-05-set-05-q08",
    "status": "svg_missing",
    "detected_type": "physics_graph",
    "priority": "high"
  },
  {
    "question_id": "hsc-physics_2ndpaper-chapter-05-set-06-q01",
    "status": "svg_missing",
    "detected_type": "physics_graph",
    "priority": "high"
  },
  {
    "question_id": "hsc-physics_2ndpaper-chapter-05-set-07-q02",
    "status": "svg_missing",
    "detected_type": "physics_graph",
    "priority": "high"
  },
  {
    "question_id": "hsc-physics_2ndpaper-chapter-05-set-08-q03",
    "status": "svg_missing",
    "detected_type": "physics_graph",
    "priority": "high"
  },
  {
    "question_id": "hsc-physics_2ndpaper-chapter-05-set-09-q04",
    "status": "svg_missing",
    "detected_type": "physics_graph",
    "priority": "high"
  },
  {
    "question_id": "hsc-physics_2ndpaper-chapter-05-set-09-q16",
    "status": "svg_missing",
    "detected_type": "physics_graph",
    "priority": "high"
  },
  {
    "question_id": "hsc-physics_2ndpaper-chapter-05-set-09-q17",
    "status": "svg_missing",
    "detected_type": "physics_graph",
    "priority": "high"
  },
  {
    "question_id": "hsc-physics_2ndpaper-chapter-05-set-10-q05",
    "status": "svg_missing",
    "detected_type": "physics_graph",
    "priority": "high"
  },
  {
    "question_id": "hsc-physics_2ndpaper-chapter-05-set-10-q24",
    "status": "svg_missing",
    "detected_type": "physics_graph",
    "priority": "high"
  },
  {
    "question_id": "hsc-physics_2ndpaper-chapter-06-set-01-q04",
    "status": "svg_missing",
    "detected_type": "physics_graph",
    "priority": "high"
  },
  {
    "question_id": "hsc-physics_2ndpaper-chapter-06-set-02-q16",
    "status": "svg_missing",
    "detected_type": "physics_graph",
    "priority": "high"
  },
  {
    "question_id": "hsc-physics_2ndpaper-chapter-06-set-03-q05",
    "status": "svg_missing",
    "detected_type": "physics_graph",
    "priority": "high"
  },
  {
    "question_id": "hsc-physics_2ndpaper-chapter-06-set-03-q18",
    "status": "svg_missing",
    "detected_type": "physics_graph",
    "priority": "high"
  },
  {
    "question_id": "hsc-physics_2ndpaper-chapter-06-set-04-q07",
    "status": "svg_missing",
    "detected_type": "physics_graph",
    "priority": "high"
  },
  {
    "question_id": "hsc-physics_2ndpaper-chapter-06-set-07-q20",
    "status": "svg_missing",
    "detected_type": "physics_graph",
    "priority": "high"
  },
  {
    "question_id": "hsc-physics_2ndpaper-chapter-06-set-08-q09",
    "status": "svg_missing",
    "detected_type": "physics_graph",
    "priority": "high"
  },
  {
    "question_id": "hsc-physics_2ndpaper-chapter-06-set-08-q21",
    "status": "svg_missing",
    "detected_type": "physics_graph",
    "priority": "high"
  },
  {
    "question_id": "hsc-physics_2ndpaper-chapter-06-set-08-q22",
    "status": "svg_missing",
    "detected_type": "physics_graph",
    "priority": "high"
  },
  {
    "question_id": "hsc-physics_2ndpaper-chapter-06-set-09-q10",
    "status": "svg_missing",
    "detected_type": "physics_graph",
    "priority": "high"
  },
  {
    "question_id": "hsc-physics_2ndpaper-chapter-06-set-09-q11",
    "status": "svg_missing",
    "detected_type": "physics_graph",
    "priority": "high"
  },
  {
    "question_id": "hsc-physics_2ndpaper-chapter-06-set-10-q18",
    "status": "svg_missing",
    "detected_type": "physics_graph",
    "priority": "high"
  },
  {
    "question_id": "hsc-physics_2ndpaper-chapter-06-set-10-q20",
    "status": "svg_missing",
    "detected_type": "physics_graph",
    "priority": "high"
  },
  {
    "question_id": "hsc-physics_2ndpaper-chapter-07-set-01-q08",
    "status": "svg_missing",
    "detected_type": "physics_graph",
    "priority": "high"
  },
  {
    "question_id": "hsc-physics_2ndpaper-chapter-07-set-02-q20",
    "status": "svg_missing",
    "detected_type": "physics_graph",
    "priority": "high"
  },
  {
    "question_id": "hsc-physics_2ndpaper-chapter-07-set-03-q09",
    "status": "svg_missing",
    "detected_type": "physics_graph",
    "priority": "high"
  },
  {
    "question_id": "hsc-physics_2ndpaper-chapter-07-set-03-q20",
    "status": "svg_missing",
    "detected_type": "physics_graph",
    "priority": "high"
  },
  {
    "question_id": "hsc-physics_2ndpaper-chapter-07-set-04-q10",
    "status": "svg_missing",
    "detected_type": "physics_graph",
    "priority": "high"
  },
  {
    "question_id": "hsc-physics_2ndpaper-chapter-07-set-07-q24",
    "status": "svg_missing",
    "detected_type": "physics_graph",
    "priority": "high"
  },
  {
    "question_id": "hsc-physics_2ndpaper-chapter-07-set-08-q13",
    "status": "svg_missing",
    "detected_type": "physics_graph",
    "priority": "high"
  },
  {
    "question_id": "hsc-physics_2ndpaper-chapter-07-set-08-q25",
    "status": "svg_missing",
    "detected_type": "physics_graph",
    "priority": "high"
  },
  {
    "question_id": "hsc-physics_2ndpaper-chapter-07-set-09-q14",
    "status": "svg_missing",
    "detected_type": "physics_graph",
    "priority": "high"
  },
  {
    "question_id": "hsc-physics_2ndpaper-chapter-07-set-09-q15",
    "status": "svg_missing",
    "detected_type": "physics_graph",
    "priority": "high"
  },
  {
    "question_id": "hsc-physics_2ndpaper-chapter-07-set-10-q22",
    "status": "svg_missing",
    "detected_type": "physics_graph",
    "priority": "high"
  },
  {
    "question_id": "hsc-physics_2ndpaper-chapter-07-set-10-q24",
    "status": "svg_missing",
    "detected_type": "physics_graph",
    "priority": "high"
  },
  {
    "question_id": "hsc-physics_2ndpaper-chapter-08-set-01-q03",
    "status": "svg_missing",
    "detected_type": "physics_graph",
    "priority": "high"
  },
  {
    "question_id": "hsc-physics_2ndpaper-chapter-08-set-02-q15",
    "status": "svg_missing",
    "detected_type": "physics_graph",
    "priority": "high"
  },
  {
    "question_id": "hsc-physics_2ndpaper-chapter-08-set-03-q04",
    "status": "svg_missing",
    "detected_type": "physics_graph",
    "priority": "high"
  },
  {
    "question_id": "hsc-physics_2ndpaper-chapter-08-set-03-q17",
    "status": "svg_missing",
    "detected_type": "physics_graph",
    "priority": "high"
  },
  {
    "question_id": "hsc-physics_2ndpaper-chapter-08-set-04-q06",
    "status": "svg_missing",
    "detected_type": "physics_graph",
    "priority": "high"
  },
  {
    "question_id": "hsc-physics_2ndpaper-chapter-08-set-07-q19",
    "status": "svg_missing",
    "detected_type": "physics_graph",
    "priority": "high"
  },
  {
    "question_id": "hsc-physics_2ndpaper-chapter-08-set-08-q08",
    "status": "svg_missing",
    "detected_type": "physics_graph",
    "priority": "high"
  },
  {
    "question_id": "hsc-physics_2ndpaper-chapter-08-set-08-q20",
    "status": "svg_missing",
    "detected_type": "physics_graph",
    "priority": "high"
  },
  {
    "question_id": "hsc-physics_2ndpaper-chapter-08-set-08-q21",
    "status": "svg_missing",
    "detected_type": "physics_graph",
    "priority": "high"
  },
  {
    "question_id": "hsc-physics_2ndpaper-chapter-08-set-09-q09",
    "status": "svg_missing",
    "detected_type": "physics_graph",
    "priority": "high"
  },
  {
    "question_id": "hsc-physics_2ndpaper-chapter-08-set-09-q10",
    "status": "svg_missing",
    "detected_type": "physics_graph",
    "priority": "high"
  },
  {
    "question_id": "hsc-physics_2ndpaper-chapter-08-set-10-q16",
    "status": "svg_missing",
    "detected_type": "physics_graph",
    "priority": "high"
  },
  {
    "question_id": "hsc-physics_2ndpaper-chapter-08-set-10-q18",
    "status": "svg_missing",
    "detected_type": "physics_graph",
    "priority": "high"
  },
  {
    "question_id": "hsc-physics_2ndpaper-chapter-09-set-01-q05",
    "status": "svg_missing",
    "detected_type": "physics_graph",
    "priority": "high"
  },
  {
    "question_id": "hsc-physics_2ndpaper-chapter-09-set-02-q17",
    "status": "svg_missing",
    "detected_type": "physics_graph",
    "priority": "high"
  },
  {
    "question_id": "hsc-physics_2ndpaper-chapter-09-set-03-q06",
    "status": "svg_missing",
    "detected_type": "physics_graph",
    "priority": "high"
  },
  {
    "question_id": "hsc-physics_2ndpaper-chapter-09-set-03-q19",
    "status": "svg_missing",
    "detected_type": "physics_graph",
    "priority": "high"
  },
  {
    "question_id": "hsc-physics_2ndpaper-chapter-09-set-04-q08",
    "status": "svg_missing",
    "detected_type": "physics_graph",
    "priority": "high"
  },
  {
    "question_id": "hsc-physics_2ndpaper-chapter-09-set-07-q21",
    "status": "svg_missing",
    "detected_type": "physics_graph",
    "priority": "high"
  },
  {
    "question_id": "hsc-physics_2ndpaper-chapter-09-set-08-q10",
    "status": "svg_missing",
    "detected_type": "physics_graph",
    "priority": "high"
  },
  {
    "question_id": "hsc-physics_2ndpaper-chapter-09-set-08-q22",
    "status": "svg_missing",
    "detected_type": "physics_graph",
    "priority": "high"
  },
  {
    "question_id": "hsc-physics_2ndpaper-chapter-09-set-08-q23",
    "status": "svg_missing",
    "detected_type": "physics_graph",
    "priority": "high"
  },
  {
    "question_id": "hsc-physics_2ndpaper-chapter-09-set-09-q11",
    "status": "svg_missing",
    "detected_type": "physics_graph",
    "priority": "high"
  },
  {
    "question_id": "hsc-physics_2ndpaper-chapter-09-set-09-q12",
    "status": "svg_missing",
    "detected_type": "physics_graph",
    "priority": "high"
  },
  {
    "question_id": "hsc-physics_2ndpaper-chapter-09-set-10-q18",
    "status": "svg_missing",
    "detected_type": "physics_graph",
    "priority": "high"
  },
  {
    "question_id": "hsc-physics_2ndpaper-chapter-09-set-10-q20",
    "status": "svg_missing",
    "detected_type": "physics_graph",
    "priority": "high"
  },
  {
    "question_id": "hsc-physics_2ndpaper-chapter-10-set-01-q08",
    "status": "svg_missing",
    "detected_type": "physics_graph",
    "priority": "high"
  },
  {
    "question_id": "hsc-physics_2ndpaper-chapter-10-set-02-q20",
    "status": "svg_missing",
    "detected_type": "physics_graph",
    "priority": "high"
  },
  {
    "question_id": "hsc-physics_2ndpaper-chapter-10-set-03-q09",
    "status": "svg_missing",
    "detected_type": "physics_graph",
    "priority": "high"
  },
  {
    "question_id": "hsc-physics_2ndpaper-chapter-10-set-03-q22",
    "status": "svg_missing",
    "detected_type": "physics_graph",
    "priority": "high"
  },
  {
    "question_id": "hsc-physics_2ndpaper-chapter-10-set-04-q11",
    "status": "svg_missing",
    "detected_type": "physics_graph",
    "priority": "high"
  },
  {
    "question_id": "hsc-physics_2ndpaper-chapter-10-set-07-q24",
    "status": "svg_missing",
    "detected_type": "physics_graph",
    "priority": "high"
  },
  {
    "question_id": "hsc-physics_2ndpaper-chapter-10-set-08-q13",
    "status": "svg_missing",
    "detected_type": "physics_graph",
    "priority": "high"
  },
  {
    "question_id": "hsc-physics_2ndpaper-chapter-10-set-08-q25",
    "status": "svg_missing",
    "detected_type": "physics_graph",
    "priority": "high"
  },
  {
    "question_id": "hsc-physics_2ndpaper-chapter-10-set-09-q14",
    "status": "svg_missing",
    "detected_type": "physics_graph",
    "priority": "high"
  },
  {
    "question_id": "hsc-physics_2ndpaper-chapter-10-set-09-q15",
    "status": "svg_missing",
    "detected_type": "physics_graph",
    "priority": "high"
  },
  {
    "question_id": "hsc-physics_2ndpaper-chapter-10-set-10-q20",
    "status": "svg_missing",
    "detected_type": "physics_graph",
    "priority": "high"
  },
  {
    "question_id": "hsc-physics_2ndpaper-chapter-10-set-10-q22",
    "status": "svg_missing",
    "detected_type": "physics_graph",
    "priority": "high"
  },
  {
    "question_id": "hsc-physics-2nd-paper-tier-a-set-02-q24",
    "status": "svg_missing",
    "detected_type": "physics_graph",
    "priority": "high"
  },
  {
    "question_id": "physics-2nd-paper-hsc-science-physics-2nd-paper-board-questions-year-wise-2024-barishal-ts-18",
    "status": "svg_missing",
    "detected_type": "physics_graph",
    "priority": "high"
  },
  {
    "question_id": "physics-2nd-paper-hsc-science-physics-2nd-paper-board-questions-year-wise-2024-barishal-ts-3",
    "status": "svg_missing",
    "detected_type": "physics_graph",
    "priority": "high"
  },
  {
    "question_id": "physics-2nd-paper-hsc-science-physics-2nd-paper-board-questions-year-wise-2024-mymensingh-ts-0",
    "status": "svg_missing",
    "detected_type": "physics_graph",
    "priority": "high"
  },
  {
    "question_id": "physics-2nd-paper-hsc-science-physics-2nd-paper-board-questions-year-wise-2024-mymensingh-ts-14",
    "status": "svg_missing",
    "detected_type": "physics_graph",
    "priority": "high"
  },
  {
    "question_id": "physics-2nd-paper-hsc-science-physics-2nd-paper-board-questions-year-wise-2024-mymensingh-ts-4",
    "status": "svg_missing",
    "detected_type": "physics_graph",
    "priority": "high"
  },
  {
    "question_id": "physics-2nd-paper-hsc-science-physics-2nd-paper-board-questions-year-wise-2024-sylhet-ts-13",
    "status": "svg_missing",
    "detected_type": "physics_graph",
    "priority": "high"
  },
  {
    "question_id": "physics-2nd-paper-hsc-science-physics-2nd-paper-board-questions-year-wise-2024-sylhet-ts-18",
    "status": "svg_missing",
    "detected_type": "physics_graph",
    "priority": "high"
  },
  {
    "question_id": "physics-2nd-paper-hsc-science-physics-2nd-paper-board-questions-year-wise-2024-sylhet-ts-8",
    "status": "svg_missing",
    "detected_type": "physics_graph",
    "priority": "high"
  },
  {
    "question_id": "physics-2nd-paper-hsc-science-physics-2nd-paper-model-tests-rajshahi-board-2024-ts-36",
    "status": "svg_missing",
    "detected_type": "math_geometry",
    "priority": "high"
  },
  {
    "question_id": "hsc-physics_2ndpaper-chapter-03-set-01-q24",
    "status": "svg_missing",
    "detected_type": "general_theory",
    "priority": "medium"
  },
  {
    "question_id": "hsc-physics_2ndpaper-chapter-03-set-02-q17",
    "status": "svg_missing",
    "detected_type": "general_theory",
    "priority": "medium"
  },
  {
    "question_id": "hsc-physics_2ndpaper-chapter-03-set-03-q10",
    "status": "svg_missing",
    "detected_type": "general_theory",
    "priority": "medium"
  },
  {
    "question_id": "hsc-physics_2ndpaper-chapter-03-set-03-q19",
    "status": "svg_missing",
    "detected_type": "general_theory",
    "priority": "medium"
  },
  {
    "question_id": "hsc-physics_2ndpaper-chapter-03-set-04-q03",
    "status": "svg_missing",
    "detected_type": "general_theory",
    "priority": "medium"
  },
  {
    "question_id": "hsc-physics_2ndpaper-chapter-03-set-04-q12",
    "status": "svg_missing",
    "detected_type": "general_theory",
    "priority": "medium"
  },
  {
    "question_id": "hsc-physics_2ndpaper-chapter-03-set-05-q05",
    "status": "svg_missing",
    "detected_type": "general_theory",
    "priority": "medium"
  },
  {
    "question_id": "hsc-physics_2ndpaper-chapter-03-set-06-q25",
    "status": "svg_missing",
    "detected_type": "general_theory",
    "priority": "medium"
  },
  {
    "question_id": "hsc-physics_2ndpaper-chapter-03-set-07-q18",
    "status": "svg_missing",
    "detected_type": "general_theory",
    "priority": "medium"
  },
  {
    "question_id": "hsc-physics_2ndpaper-chapter-03-set-08-q11",
    "status": "svg_missing",
    "detected_type": "general_theory",
    "priority": "medium"
  },
  {
    "question_id": "hsc-physics_2ndpaper-chapter-03-set-08-q20",
    "status": "svg_missing",
    "detected_type": "general_theory",
    "priority": "medium"
  },
  {
    "question_id": "hsc-physics_2ndpaper-chapter-03-set-09-q04",
    "status": "svg_missing",
    "detected_type": "general_theory",
    "priority": "medium"
  },
  {
    "question_id": "hsc-physics_2ndpaper-chapter-03-set-09-q13",
    "status": "svg_missing",
    "detected_type": "general_theory",
    "priority": "medium"
  },
  {
    "question_id": "hsc-physics_2ndpaper-chapter-03-set-10-q06",
    "status": "svg_missing",
    "detected_type": "general_theory",
    "priority": "medium"
  },
  {
    "question_id": "hsc-physics_2ndpaper-chapter-04-set-07-q25",
    "status": "svg_missing",
    "detected_type": "general_theory",
    "priority": "medium"
  },
  {
    "question_id": "hsc-physics_2ndpaper-chapter-04-set-08-q14",
    "status": "svg_missing",
    "detected_type": "general_theory",
    "priority": "medium"
  },
  {
    "question_id": "hsc-physics_2ndpaper-chapter-05-set-08-q16",
    "status": "svg_missing",
    "detected_type": "general_theory",
    "priority": "medium"
  },
  {
    "question_id": "hsc-physics_2ndpaper-chapter-06-set-07-q22",
    "status": "svg_missing",
    "detected_type": "general_theory",
    "priority": "medium"
  },
  {
    "question_id": "hsc-physics_2ndpaper-chapter-06-set-08-q11",
    "status": "svg_missing",
    "detected_type": "general_theory",
    "priority": "medium"
  },
  {
    "question_id": "hsc-physics_2ndpaper-chapter-07-set-08-q15",
    "status": "svg_missing",
    "detected_type": "general_theory",
    "priority": "medium"
  },
  {
    "question_id": "hsc-physics_2ndpaper-chapter-08-set-07-q21",
    "status": "svg_missing",
    "detected_type": "general_theory",
    "priority": "medium"
  },
  {
    "question_id": "hsc-physics_2ndpaper-chapter-08-set-08-q10",
    "status": "svg_missing",
    "detected_type": "general_theory",
    "priority": "medium"
  },
  {
    "question_id": "hsc-physics_2ndpaper-chapter-09-set-07-q23",
    "status": "svg_missing",
    "detected_type": "general_theory",
    "priority": "medium"
  },
  {
    "question_id": "hsc-physics_2ndpaper-chapter-09-set-08-q12",
    "status": "svg_missing",
    "detected_type": "general_theory",
    "priority": "medium"
  },
  {
    "question_id": "hsc-physics_2ndpaper-chapter-10-set-01-q04",
    "status": "svg_missing",
    "detected_type": "general_theory",
    "priority": "medium"
  },
  {
    "question_id": "hsc-physics_2ndpaper-chapter-10-set-02-q03",
    "status": "svg_missing",
    "detected_type": "general_theory",
    "priority": "medium"
  },
  {
    "question_id": "hsc-physics_2ndpaper-chapter-10-set-03-q02",
    "status": "svg_missing",
    "detected_type": "general_theory",
    "priority": "medium"
  },
  {
    "question_id": "hsc-physics_2ndpaper-chapter-10-set-04-q01",
    "status": "svg_missing",
    "detected_type": "general_theory",
    "priority": "medium"
  },
  {
    "question_id": "hsc-physics_2ndpaper-chapter-10-set-05-q06",
    "status": "svg_missing",
    "detected_type": "general_theory",
    "priority": "medium"
  },
  {
    "question_id": "hsc-physics_2ndpaper-chapter-10-set-06-q05",
    "status": "svg_missing",
    "detected_type": "general_theory",
    "priority": "medium"
  },
  {
    "question_id": "hsc-physics_2ndpaper-chapter-10-set-07-q04",
    "status": "svg_missing",
    "detected_type": "general_theory",
    "priority": "medium"
  },
  {
    "question_id": "hsc-physics_2ndpaper-chapter-10-set-08-q03",
    "status": "svg_missing",
    "detected_type": "general_theory",
    "priority": "medium"
  },
  {
    "question_id": "hsc-physics_2ndpaper-chapter-10-set-08-q15",
    "status": "svg_missing",
    "detected_type": "general_theory",
    "priority": "medium"
  },
  {
    "question_id": "hsc-physics_2ndpaper-chapter-10-set-09-q02",
    "status": "svg_missing",
    "detected_type": "general_theory",
    "priority": "medium"
  },
  {
    "question_id": "hsc-physics_2ndpaper-chapter-10-set-10-q01",
    "status": "svg_missing",
    "detected_type": "general_theory",
    "priority": "medium"
  },
  {
    "question_id": "physics-2nd-paper-hsc-science-physics-2nd-paper-board-questions-year-wise-2024-barishal-ts-23",
    "status": "svg_missing",
    "detected_type": "general_theory",
    "priority": "medium"
  },
  {
    "question_id": "physics-2nd-paper-hsc-science-physics-2nd-paper-model-tests-rajshahi-board-2024-ts-5",
    "status": "svg_missing",
    "detected_type": "general_theory",
    "priority": "medium"
  },
  {
    "question_id": "physics-2nd-paper-hsc-science-physics-2nd-paper-model-tests-rajshahi-board-2024-ts-9",
    "status": "svg_missing",
    "detected_type": "general_theory",
    "priority": "medium"
  },
  {
    "question_id": "hsc-physics_2ndpaper-chapter-06-set-01-q02",
    "status": "svg_missing",
    "detected_type": "general_theory",
    "priority": "low"
  },
  {
    "question_id": "hsc-physics_2ndpaper-chapter-06-set-02-q01",
    "status": "svg_missing",
    "detected_type": "general_theory",
    "priority": "low"
  },
  {
    "question_id": "hsc-physics_2ndpaper-chapter-06-set-03-q02",
    "status": "svg_missing",
    "detected_type": "general_theory",
    "priority": "low"
  },
  {
    "question_id": "hsc-physics_2ndpaper-chapter-06-set-04-q01",
    "status": "svg_missing",
    "detected_type": "general_theory",
    "priority": "low"
  },
  {
    "question_id": "hsc-physics_2ndpaper-chapter-06-set-05-q02",
    "status": "svg_missing",
    "detected_type": "general_theory",
    "priority": "low"
  },
  {
    "question_id": "hsc-physics_2ndpaper-chapter-06-set-06-q01",
    "status": "svg_missing",
    "detected_type": "general_theory",
    "priority": "low"
  },
  {
    "question_id": "hsc-physics_2ndpaper-chapter-06-set-07-q02",
    "status": "svg_missing",
    "detected_type": "general_theory",
    "priority": "low"
  },
  {
    "question_id": "hsc-physics_2ndpaper-chapter-06-set-08-q01",
    "status": "svg_missing",
    "detected_type": "general_theory",
    "priority": "low"
  },
  {
    "question_id": "hsc-physics_2ndpaper-chapter-06-set-09-q02",
    "status": "svg_missing",
    "detected_type": "general_theory",
    "priority": "low"
  },
  {
    "question_id": "hsc-physics_2ndpaper-chapter-06-set-10-q01",
    "status": "svg_missing",
    "detected_type": "general_theory",
    "priority": "low"
  },
  {
    "question_id": "physics-2nd-paper-hsc-science-physics-2nd-paper-most-important-ai-prediction-set-1-ts-10",
    "status": "svg_missing",
    "detected_type": "general_theory",
    "priority": "low"
  }
]
