{
  "hsc-biology-2nd-paper-chapter-07-high-priority-set-03-q01": {
    "correctOption": "হাঁটুতে",
    "explanation": "হাঁটুতে"
  },
  "hsc-biology-2nd-paper-chapter-07-high-priority-set-03-q02": {
    "correctOption": "অ্যাকটিন ও মায়োসিন উভয়ই",
    "explanation": "A-band হলো পেশির গাঢ় অংশ। এই অংশে পুরু মায়োসিন ফিলামেন্ট থাকে এবং এর ফাঁকে ফাঁকে পাতলা অ্যাকটিন ফিলামেন্ট প্রবেশ করে থাকে। তাই এতে উভয় প্রোটিনই থাকে। I-band এ কেবল অ্যাকটিন থাকে।"
  },
  "hsc-biology-2nd-paper-chapter-07-high-priority-set-03-q03": {
    "correctOption": "কব্জা সন্ধি (Hinge joint)",
    "explanation": "দরজার কবজার মতো যে সন্ধি কেবল এক তলে নড়াচড়া করতে পারে, তাকে কব্জা বা হিঞ্জ জয়েন্ট বলে। কনুই ও হাঁটুর সন্ধি এর প্রকৃষ্ট উদাহরণ। কাঁধ ও উরুর সন্ধি হলো বল ও কোটর।"
  },
  "hsc-biology-2nd-paper-chapter-07-high-priority-set-03-q04": {
    "correctOption": "স্ক্যাপুলা",
    "explanation": "স্ক্যাপুলা"
  },
  "hsc-biology-2nd-paper-chapter-07-high-priority-set-03-q05": {
    "correctOption": "প্রাকৃতিক নির্বাচন (Natural Selection)",
    "explanation": "ডারউইনের মতবাদের মূল ভিত্তিই হলো 'প্রাকৃতিক নির্বাচন' বা যোগ্যতমের টিকে থাকা (Survival of the fittest)। প্রকৃতি সেই জীবকেই নির্বাচন করে যার পরিবেশের সাথে অভিযোজিত হওয়ার ক্ষমতা সবচেয়ে বেশি।"
  },
  "hsc-biology-2nd-paper-chapter-07-high-priority-set-03-q06": {
    "correctOption": "অ্যাকোমোডেশন (Accommodation)",
    "explanation": "অ্যাকোমোডেশন হলো চোখের লেন্সের বক্রতা পরিবর্তন করে দূর ও নিকটের বস্তু স্পষ্ট দেখার ক্ষমতা।"
  },
  "hsc-biology-2nd-paper-chapter-07-high-priority-set-03-q07": {
    "correctOption": "মেসোডার্ম (Mesoderm)",
    "explanation": "মেসোডার্ম (Mesoderm)"
  },
  "hsc-biology-2nd-paper-chapter-07-high-priority-set-03-q08": {
    "correctOption": "পেরিকন্ড্রিয়াম",
    "explanation": "তরুণাস্থির বাইরের মসৃণ আবরণকে পেরিকন্ড্রিয়াম বলে।"
  },
  "hsc-biology-2nd-paper-chapter-07-high-priority-set-03-q09": {
    "correctOption": "পেরিকন্ড্রিয়াম",
    "explanation": "পেরিকন্ড্রিয়াম"
  },
  "hsc-biology-2nd-paper-chapter-07-high-priority-set-03-q10": {
    "correctOption": "সাইনোভিয়াল ফ্লুইড",
    "explanation": "সাইনোভিয়াল ফ্লুইড"
  },
  "hsc-biology-2nd-paper-chapter-07-high-priority-set-03-q11": {
    "correctOption": "লিগামেন্ট",
    "explanation": "লিগামেন্ট"
  },
  "hsc-biology-2nd-paper-chapter-07-high-priority-set-03-q12": {
    "correctOption": "সিলিয়ারি পেশি (Ciliary muscle)",
    "explanation": "সিলিয়ারি বডির সিলিয়ারি পেশির সংকোচন প্রসারণের ফলে সাসপেনসরি লিগামেন্টে টান পড়ে বা শিথিল হয়, যার ফলে লেন্স সরু বা মোটা হয়ে উপযোজন সম্পন্ন করে।"
  },
  "hsc-biology-2nd-paper-chapter-07-high-priority-set-03-q13": {
    "correctOption": "৭টি",
    "explanation": "৭টি"
  },
  "hsc-biology-2nd-paper-chapter-07-high-priority-set-03-q14": {
    "correctOption": "টেন্ডন (Tendon / পেশিতে অস্থি)",
    "explanation": "টেন্ডন (Tendon / পেশিতে অস্থি)"
  },
  "hsc-biology-2nd-paper-chapter-07-high-priority-set-03-q15": {
    "correctOption": "৭ জোড়া",
    "explanation": "৭ জোড়া"
  },
  "hsc-biology-2nd-paper-chapter-07-high-priority-set-03-q16": {
    "correctOption": "সেরিব্রাম (Cerebrum)",
    "explanation": "সেরিব্রাম (Cerebrum)"
  },
  "hsc-biology-2nd-paper-chapter-07-high-priority-set-03-q17": {
    "correctOption": "ফেনেস্ট্রা ওভালিস",
    "explanation": "স্টেপিস অস্থি ফেনেস্ট্রা ওভালিস বা ওভাল উইন্ডোর মাধ্যমে অন্তঃকর্ণে শব্দ প্রবেশ করায়।"
  },
  "hsc-biology-2nd-paper-chapter-07-high-priority-set-03-q18": {
    "correctOption": "ফ্রন্টাল অস্থি (Frontal Bone)",
    "explanation": "ফ্রন্টাল অস্থি (Frontal Bone)"
  },
  "hsc-biology-2nd-paper-chapter-07-high-priority-set-03-q19": {
    "correctOption": "ফ্রন্টাল লোব",
    "explanation": "ফ্রন্টাল লোবের প্রিকেন্ট্রাল জাইরাসে প্রাইমারি মোটর এরিয়া অবস্থিত, যা স্বেচ্ছাকৃত পেশি নিয়ন্ত্রণ করে।"
  },
  "hsc-biology-2nd-paper-chapter-07-high-priority-set-03-q20": {
    "correctOption": "১২",
    "explanation": "১২"
  },
  "hsc-biology-2nd-paper-chapter-07-high-priority-set-03-q21": {
    "correctOption": "৮টি",
    "explanation": "৮টি"
  },
  "hsc-biology-2nd-paper-chapter-07-high-priority-set-03-q22": {
    "correctOption": "১১শ এবং ১২শ জোড়া",
    "explanation": "১১শ এবং ১২শ জোড়া"
  },
  "hsc-biology-2nd-paper-chapter-07-high-priority-set-03-q23": {
    "correctOption": "স্ক্যাপুলা ও ক্ল্যাভিকল",
    "explanation": "বক্ষোচক্র স্ক্যাপুলা (Scapula) এবং ক্ল্যাভিকল (Clavicle) দিয়ে গঠিত।"
  },
  "hsc-biology-2nd-paper-chapter-07-high-priority-set-03-q24": {
    "correctOption": "অ্যাটলাস ও অ্যাক্সিসের মধ্যবর্তী সন্ধি",
    "explanation": "অ্যাটলাস (C1) ও অ্যাক্সিস (C2) কশেরুকার মধ্যবর্তী সন্ধি পিভট জয়েন্টের উদাহরণ, যা মাথা ঘোরাতে সাহায্য করে।"
  },
  "hsc-biology-2nd-paper-chapter-07-high-priority-set-03-q25": {
    "correctOption": "নিতম্ব (Hip joint)",
    "explanation": "নিতম্বের সন্ধি বল ও সকেট জয়েন্টের উদাহরণ, যা সব দিকে ঘূর্ণন সক্ষম।"
  }
}
