[
  {
    "id": "hsc-biology-1st-paper-chapter-09-set-07-q01",
    "subject": "biology-1st-paper",
    "chapter": "hsc-biology-1st-paper-chapter-09-set-07",
    "text": "কোনটি C₃ চক্রের জন্য সঠিক?",
    "options": [
      "আদর্শ তাপমাত্রা ৩০° সে.—৪৫° সে.",
      "ক্লোরোপ্লাস্টের স্ট্রোমাতে হয়",
      "প্রথম উৎপন্ন দ্রব্য ফসফোগ্লিসারিক এসিড",
      "CO₂ এর ঘনত্ব ০.১০—১০ ppm দরকার"
    ],
    "image": null,
    "optionImages": null,
    "timeLimit": 45
  },
  {
    "id": "hsc-biology-1st-paper-chapter-09-set-07-q02",
    "subject": "biology-1st-paper",
    "chapter": "hsc-biology-1st-paper-chapter-09-set-07",
    "text": "কোনটি নাইট্রোজেন বেস শুধু রাইবোজের সাথে যুক্ত হয়?",
    "options": [
      "থাইমিন",
      "অ্যাডেনিন",
      "ইউরাসিল",
      "গুয়ানিন"
    ],
    "image": null,
    "optionImages": null,
    "timeLimit": 45
  },
  {
    "id": "hsc-biology-1st-paper-chapter-09-set-07-q03",
    "subject": "biology-1st-paper",
    "chapter": "hsc-biology-1st-paper-chapter-09-set-07",
    "text": "ক্রেবস চক্রে এক অণু এসিটাইল কো-এ থেকে মোট কত অণু ATP তৈরি হয়?",
    "options": [
      "৮",
      "৬",
      "১২",
      "২৪"
    ],
    "image": null,
    "optionImages": null,
    "timeLimit": 45
  },
  {
    "id": "hsc-biology-1st-paper-chapter-09-set-07-q04",
    "subject": "biology-1st-paper",
    "chapter": "hsc-biology-1st-paper-chapter-09-set-07",
    "text": "গ্লাইকোলাইসিস প্রক্রিয়ায় এক অণু গ্লুকোজ হতে নিট কতটি ATP উৎপন্ন হয়?",
    "options": [
      "৮",
      "৩",
      "২",
      "৪"
    ],
    "image": null,
    "optionImages": null,
    "timeLimit": 45
  },
  {
    "id": "hsc-biology-1st-paper-chapter-09-set-07-q05",
    "subject": "biology-1st-paper",
    "chapter": "hsc-biology-1st-paper-chapter-09-set-07",
    "text": "গ্লাইকোলাইসিসের বিক্রিয়াসমূহ কোথায় সংঘটিত হয়?",
    "options": [
      "ক্লোরোপ্লাস্টে",
      "নিউক্লিওপ্লাজমে",
      "মাইটোকন্ড্রিয়ায়",
      "সাইটোপ্লাজমে"
    ],
    "image": null,
    "optionImages": null,
    "timeLimit": 45
  },
  {
    "id": "hsc-biology-1st-paper-chapter-09-set-07-q06",
    "subject": "biology-1st-paper",
    "chapter": "hsc-biology-1st-paper-chapter-09-set-07",
    "text": "তীর দ্বারা চিহ্নিত দশাটি যে পরজীবীর তার বৈশিষ্ট্য হলো— i. এর জীবনচক্রে দুইটি পোষকের প্রয়োজন ii. যৌন জননে এক্সফ্ল্যাজেলেশন দশা থাকে iii. রক্ত লোহিত কণিকা ধ্বংস করে এবং শরীরে ঘাম বের হয় নিচের কোনটি সঠিক? ২৩। উদ্দীপকটি পড় এবং ২৩ ও ২৪ নং প্রশ্নের উত্তর দাও : (সবাত ও অবাত শ্বসনের বর্ণনা) ২৩। উদ্দীপকটি পড় এবং ২৩ ও ২৪ নং প্রশ্নের উত্তর দাও : (সবাত ও অবাত শ্বসনের বর্ণনা))",
    "options": [
      "i ও iii",
      "i ও ii",
      "ii ও iii",
      "i, ii ও iii"
    ],
    "image": "/images/quiz/premium/hsc-biology-1st-paper-chapter-09-set-07-q06.svg",
    "optionImages": null,
    "timeLimit": 45
  },
  {
    "id": "hsc-biology-1st-paper-chapter-09-set-07-q07",
    "subject": "biology-1st-paper",
    "chapter": "hsc-biology-1st-paper-chapter-09-set-07",
    "text": "নিচের কোনটি ম্যাক্রো মৌল?",
    "options": [
      "ক্লোরিন",
      "ম্যাঙ্গানিজ",
      "সোডিয়াম",
      "নাইট্রোজেন"
    ],
    "image": null,
    "optionImages": null,
    "timeLimit": 45
  },
  {
    "id": "hsc-biology-1st-paper-chapter-09-set-07-q08",
    "subject": "biology-1st-paper",
    "chapter": "hsc-biology-1st-paper-chapter-09-set-07",
    "text": "নিচের কোনটি সক্রিয় পরিশোষণের ক্ষেত্রে প্রযোজ্য?",
    "options": [
      "লুন্ডেগড় মতবাদ",
      "ব্যাপক প্রবাহ মতবাদ",
      "ডোনান সাম্যাবস্থা মতবাদ",
      "ব্যাপন মতবাদ"
    ],
    "image": null,
    "optionImages": null,
    "timeLimit": 45
  },
  {
    "id": "hsc-biology-1st-paper-chapter-09-set-07-q09",
    "subject": "biology-1st-paper",
    "chapter": "hsc-biology-1st-paper-chapter-09-set-07",
    "text": "প্রক্রিয়াটির 'P' ব্যবহৃত ধাপে— (ইলেকট্রন ট্রান্সপোর্ট চেইন) i. ম্যাট্রিক্সে পানি তৈরি হয় ii. কেমি অসমোসিস প্রক্রিয়ায় ATP তৈরি হয় iii. মাইটোকন্ড্রিয়ার মেমব্রেন অংশগ্রহণ করে নিচের কোনটি সঠিক?",
    "options": [
      "i, ii ও iii",
      "i ও ii",
      "ii ও iii",
      "i ও iii"
    ],
    "image": null,
    "optionImages": null,
    "timeLimit": 45
  },
  {
    "id": "hsc-biology-1st-paper-chapter-09-set-07-q10",
    "subject": "biology-1st-paper",
    "chapter": "hsc-biology-1st-paper-chapter-09-set-07",
    "text": "সক্রিয় পরিশোষণে— i. শ্বসন হার স্বাভাবিক থাকে ii. বাহক আয়ন বা অণু দ্বারা সম্পন্ন হয় iii. এনজাইম গুরুত্বপূর্ণ ভূমিকা রাখে নিচের কোনটি সঠিক?",
    "options": [
      "ii ও iii",
      "i ও ii",
      "i, ii ও iii",
      "i ও iii"
    ],
    "image": null,
    "optionImages": null,
    "timeLimit": 45
  },
  {
    "id": "hsc-biology-1st-paper-chapter-09-set-07-q11",
    "subject": "biology-1st-paper",
    "chapter": "hsc-biology-1st-paper-chapter-09-set-07",
    "text": "সক্রিয় লবণ পরিশোষণ মতবাদ কোনটি?",
    "options": [
      "আয়ন বিনিময় মতবাদ",
      "লুন্ডেগড় মতবাদ",
      "ডোনান সাম্যাবস্থা মতবাদ",
      "ব্যাপক প্রবাহ মতবাদ"
    ],
    "image": null,
    "optionImages": null,
    "timeLimit": 45
  },
  {
    "id": "hsc-biology-1st-paper-chapter-09-set-07-q12",
    "subject": "biology-1st-paper",
    "chapter": "hsc-biology-1st-paper-chapter-09-set-07",
    "text": "সবাত ও অবাত শ্বসনের অভিন্ন ধাপ কোনটি?",
    "options": [
      "ক্রেবস চক্র",
      "ইলেকট্রন প্রবাহতন্ত্র",
      "অ্যাসিটাইল কো-এ সৃষ্টি",
      "গ্লাইকোলাইসিস"
    ],
    "image": null,
    "optionImages": null,
    "timeLimit": 45
  },
  {
    "id": "hsc-biology-1st-paper-chapter-09-set-07-q13",
    "subject": "biology-1st-paper",
    "chapter": "hsc-biology-1st-paper-chapter-09-set-07",
    "text": "হাইডাথোড দিয়ে তরল পানি বের হয়ে যাওয়াকে বলে—",
    "options": [
      "প্রস্বেদন",
      "গাটেশন",
      "অসমোসিস",
      "ডিফিউশন"
    ],
    "image": null,
    "optionImages": null,
    "timeLimit": 45
  },
  {
    "id": "hsc-biology-1st-paper-chapter-09-set-07-q14",
    "subject": "biology-1st-paper",
    "chapter": "hsc-biology-1st-paper-chapter-09-set-07",
    "text": "C3 চক্র বা কেলভিন-বেনসন চক্রে প্রথম উৎপন্ন হওয়া ৩ কার্বন বিশিষ্ট স্থায়ী পদার্থটির নাম কী?",
    "options": [
      "৩-ফসফোগ্লিসারিক এসিড (3-PGA)",
      "রাইবুলোজ ৫-ফসফেট",
      "গ্লুকোজ",
      "ম্যালিক এসিড"
    ],
    "image": null,
    "optionImages": null,
    "timeLimit": 45
  },
  {
    "id": "hsc-biology-1st-paper-chapter-09-set-07-q15",
    "subject": "biology-1st-paper",
    "chapter": "hsc-biology-1st-paper-chapter-09-set-07",
    "text": "C4 উদ্ভিদে ক্র্যাঞ্জ অ্যানাটমি থাকার কারণে তারা কত তাপমাত্রায় শালোকসংশ্লেষণ খুব ভালোভাবে চালিয়ে নিতে পারে (যেমন ভুট্টা, ইক্ষু)?",
    "options": [
      "০-১০ ডিগ্রি সে.",
      "১৫-২০ ডিগ্রি সে.",
      "৬০ ডিগ্রির উপরে",
      "৩০-৪৫ ডিগ্রি সে. উচ্চতাপে"
    ],
    "image": null,
    "optionImages": null,
    "timeLimit": 45
  },
  {
    "id": "hsc-biology-1st-paper-chapter-09-set-07-q16",
    "subject": "biology-1st-paper",
    "chapter": "hsc-biology-1st-paper-chapter-09-set-07",
    "text": "C₃ উদ্ভিদে উচ্চ তাপমাত্রায় কোন প্রক্রিয়া বেশি হয়?",
    "options": [
      "টিস্যু কালচার",
      "গাজন",
      "ফটোশ্বসন",
      "নাইট্রিফিকেশন"
    ],
    "image": null,
    "optionImages": null,
    "timeLimit": 45
  },
  {
    "id": "hsc-biology-1st-paper-chapter-09-set-07-q17",
    "subject": "biology-1st-paper",
    "chapter": "hsc-biology-1st-paper-chapter-09-set-07",
    "text": "C₃ চক্রের প্রথম স্থায়ী পদার্থ কোনটি?",
    "options": [
      "OAA",
      "ম্যালিক অ্যাসিড",
      "3-PGA",
      "গ্লুকোজ"
    ],
    "image": null,
    "optionImages": null,
    "timeLimit": 45
  },
  {
    "id": "hsc-biology-1st-paper-chapter-09-set-07-q18",
    "subject": "biology-1st-paper",
    "chapter": "hsc-biology-1st-paper-chapter-09-set-07",
    "text": "C₄ উদ্ভিদে প্রথম স্থায়ী পদার্থ কোনটি?",
    "options": [
      "গ্লুকোজ",
      "3-PGA",
      "OAA",
      "রুবিসকো"
    ],
    "image": null,
    "optionImages": null,
    "timeLimit": 45
  },
  {
    "id": "hsc-biology-1st-paper-chapter-09-set-07-q19",
    "subject": "biology-1st-paper",
    "chapter": "hsc-biology-1st-paper-chapter-09-set-07",
    "text": "C₄ উদ্ভিদের উদাহরণ কোনটি?",
    "options": [
      "ধান",
      "গম",
      "ভুট্টা",
      "আলু"
    ],
    "image": null,
    "optionImages": null,
    "timeLimit": 45
  },
  {
    "id": "hsc-biology-1st-paper-chapter-09-set-07-q20",
    "subject": "biology-1st-paper",
    "chapter": "hsc-biology-1st-paper-chapter-09-set-07",
    "text": "ETC কোথায় থাকে?",
    "options": [
      "নিউক্লিয়ার মেমব্রেন",
      "মাইটোকন্ড্রিয়ার অন্তঃঝিল্লি",
      "সাইটোপ্লাজম",
      "কোষপ্রাচীর"
    ],
    "image": null,
    "optionImages": null,
    "timeLimit": 45
  },
  {
    "id": "hsc-biology-1st-paper-chapter-09-set-07-q21",
    "subject": "biology-1st-paper",
    "chapter": "hsc-biology-1st-paper-chapter-09-set-07",
    "text": "High-priority practice: C₃ উদ্ভিদে উচ্চ তাপমাত্রায় কোন প্রক্রিয়া বেশি হয়?",
    "options": [
      "ফটোশ্বসন",
      "নাইট্রিফিকেশন",
      "টিস্যু কালচার",
      "গাজন"
    ],
    "image": null,
    "optionImages": null,
    "timeLimit": 45
  },
  {
    "id": "hsc-biology-1st-paper-chapter-09-set-07-q22",
    "subject": "biology-1st-paper",
    "chapter": "hsc-biology-1st-paper-chapter-09-set-07",
    "text": "High-priority practice: C₃ চক্রের প্রথম স্থায়ী পদার্থ কোনটি?",
    "options": [
      "3-PGA",
      "ম্যালিক অ্যাসিড",
      "OAA",
      "গ্লুকোজ"
    ],
    "image": null,
    "optionImages": null,
    "timeLimit": 45
  },
  {
    "id": "hsc-biology-1st-paper-chapter-09-set-07-q23",
    "subject": "biology-1st-paper",
    "chapter": "hsc-biology-1st-paper-chapter-09-set-07",
    "text": "High-priority practice: C₄ উদ্ভিদে প্রথম স্থায়ী পদার্থ কোনটি?",
    "options": [
      "OAA",
      "গ্লুকোজ",
      "3-PGA",
      "রুবিসকো"
    ],
    "image": null,
    "optionImages": null,
    "timeLimit": 45
  },
  {
    "id": "hsc-biology-1st-paper-chapter-09-set-07-q24",
    "subject": "biology-1st-paper",
    "chapter": "hsc-biology-1st-paper-chapter-09-set-07",
    "text": "High-priority practice: ETC কোথায় থাকে?",
    "options": [
      "কোষপ্রাচীর",
      "মাইটোকন্ড্রিয়ার অন্তঃঝিল্লি",
      "সাইটোপ্লাজম",
      "নিউক্লিয়ার মেমব্রেন"
    ],
    "image": null,
    "optionImages": null,
    "timeLimit": 45
  },
  {
    "id": "hsc-biology-1st-paper-chapter-09-set-07-q25",
    "subject": "biology-1st-paper",
    "chapter": "hsc-biology-1st-paper-chapter-09-set-07",
    "text": "High-priority practice: উদ্ভিদ শোষিত পানির অধিকাংশ কোন প্রক্রিয়ায় হারায়?",
    "options": [
      "প্রস্বেদন",
      "নিষেক",
      "পরাগায়ন",
      "শ্বসন"
    ],
    "image": null,
    "optionImages": null,
    "timeLimit": 45
  }
]
