[
  {
    "id": "hsc-biology-1st-paper-chapter-04-set-10-q01",
    "subject": "biology-1st-paper",
    "chapter": "hsc-biology-1st-paper-chapter-04-set-10",
    "text": "ইনফ্লুয়েঞ্জা বা সাধারণ সর্দিকাশির ভাইরাসের প্রকৃতি কেমন?",
    "options": [
      "ব্যাঙাচি আকৃতির",
      "গোলাকার",
      "দণ্ডাকার",
      "বহুতলক"
    ],
    "image": null,
    "optionImages": null,
    "timeLimit": 45
  },
  {
    "id": "hsc-biology-1st-paper-chapter-04-set-10-q02",
    "subject": "biology-1st-paper",
    "chapter": "hsc-biology-1st-paper-chapter-04-set-10",
    "text": "উদ্দীপকের চিত্র 'Q' দ্বারা প্রদর্শিত প্রযুক্তিটি ব্যবহৃত হয়— (রিকম্বিনেন্ট প্লাজমিড) i. রোগ প্রতিরোধী জাত উৎপাদনে ii. ট্রান্সজেনিক উদ্ভিদ উৎপাদনে iii. ইনসুলিন উৎপাদনে নিচের কোনটি সঠিক?",
    "options": [
      "ii ও iii",
      "i ও ii",
      "i ও iii",
      "i, ii ও iii"
    ],
    "image": "/images/quiz/premium/hsc-biology-1st-paper-chapter-04-set-10-q02.svg",
    "optionImages": null,
    "timeLimit": 45
  },
  {
    "id": "hsc-biology-1st-paper-chapter-04-set-10-q03",
    "subject": "biology-1st-paper",
    "chapter": "hsc-biology-1st-paper-chapter-04-set-10",
    "text": "এডিস মশা দিয়ে কোন মরণঘাতী আরএনএ ভাইরাস ছড়ায় যা 'ব্রেক বোন ফিভার' সৃষ্টি করে?",
    "options": [
      "র্যাবিস",
      "টিটু ফায",
      "পোলিও ভাইরাস",
      "ডেঙ্গু ফ্লাভি ভাইরাস"
    ],
    "image": null,
    "optionImages": null,
    "timeLimit": 45
  },
  {
    "id": "hsc-biology-1st-paper-chapter-04-set-10-q04",
    "subject": "biology-1st-paper",
    "chapter": "hsc-biology-1st-paper-chapter-04-set-10",
    "text": "কলেরা রোগের জীবাণু কোনটি?",
    "options": [
      "Vibrio cholerae",
      "Penicillium",
      "Plasmodium",
      "TMV"
    ],
    "image": null,
    "optionImages": null,
    "timeLimit": 45
  },
  {
    "id": "hsc-biology-1st-paper-chapter-04-set-10-q05",
    "subject": "biology-1st-paper",
    "chapter": "hsc-biology-1st-paper-chapter-04-set-10",
    "text": "কলেরার জন্য দায়ী ভিব্রিও কলেরি (Vibrio cholerae) ব্যাকটেরিয়াটি আকৃতিতে কেমন হয়?",
    "options": [
      "দণ্ডাকার",
      "গোলাকার",
      "কমা (Comma) আকৃতির",
      "স্পাইরাল"
    ],
    "image": null,
    "optionImages": null,
    "timeLimit": 45
  },
  {
    "id": "hsc-biology-1st-paper-chapter-04-set-10-q06",
    "subject": "biology-1st-paper",
    "chapter": "hsc-biology-1st-paper-chapter-04-set-10",
    "text": "কলেরার জীবাণু কোনটি?",
    "options": [
      "HIV",
      "TMV",
      "Vibrio cholerae",
      "Plasmodium vivax"
    ],
    "image": null,
    "optionImages": null,
    "timeLimit": 45
  },
  {
    "id": "hsc-biology-1st-paper-chapter-04-set-10-q07",
    "subject": "biology-1st-paper",
    "chapter": "hsc-biology-1st-paper-chapter-04-set-10",
    "text": "কোন উপাদানের কারণে গ্রাম পজিটিভ (Gram-positive) ব্যাকটেরিয়া ক্রিস্টাল ভায়োলেট রং ধারণ করতে সক্ষম?",
    "options": [
      "ফ্লাজেলা",
      "টিকোয়িক এসিড",
      "মেসোজোম",
      "প্রচুর পরিমাণ পেপটিডোগ্লাইক্যানের কারণে"
    ],
    "image": null,
    "optionImages": null,
    "timeLimit": 45
  },
  {
    "id": "hsc-biology-1st-paper-chapter-04-set-10-q08",
    "subject": "biology-1st-paper",
    "chapter": "hsc-biology-1st-paper-chapter-04-set-10",
    "text": "ডেঙ্গু ভাইরাস কোন মশার মাধ্যমে ছড়ায়?",
    "options": [
      "এডিস",
      "কিউলেক্স",
      "অ্যানোফিলিস",
      "ম্যানসোনিয়া"
    ],
    "image": null,
    "optionImages": null,
    "timeLimit": 45
  },
  {
    "id": "hsc-biology-1st-paper-chapter-04-set-10-q09",
    "subject": "biology-1st-paper",
    "chapter": "hsc-biology-1st-paper-chapter-04-set-10",
    "text": "ডেঙ্গু রোগের বাহক কোনটি?",
    "options": [
      "মাছি",
      "Aedes মশা",
      "Culex মশা",
      "Anopheles মশা"
    ],
    "image": null,
    "optionImages": null,
    "timeLimit": 45
  },
  {
    "id": "hsc-biology-1st-paper-chapter-04-set-10-q10",
    "subject": "biology-1st-paper",
    "chapter": "hsc-biology-1st-paper-chapter-04-set-10",
    "text": "দণ্ডাকার ভাইরাসের উদাহরণ কোনটি?",
    "options": [
      "TMV",
      "T₂ phage",
      "HIV",
      "Vaccinia"
    ],
    "image": null,
    "optionImages": null,
    "timeLimit": 45
  },
  {
    "id": "hsc-biology-1st-paper-chapter-04-set-10-q11",
    "subject": "biology-1st-paper",
    "chapter": "hsc-biology-1st-paper-chapter-04-set-10",
    "text": "নাইট্রোজেন স্থিরকারী ব্যাকটেরিয়ার উদাহরণ কোনটি?",
    "options": [
      "Plasmodium",
      "E. coli",
      "Rhizobium",
      "TMV"
    ],
    "image": null,
    "optionImages": null,
    "timeLimit": 45
  },
  {
    "id": "hsc-biology-1st-paper-chapter-04-set-10-q12",
    "subject": "biology-1st-paper",
    "chapter": "hsc-biology-1st-paper-chapter-04-set-10",
    "text": "নিউমোনিয়ার জীবাণু সাধারণত কোন ধরনের?",
    "options": [
      "ব্যাকটেরিয়া",
      "শৈবাল",
      "ভাইরাস মাত্র",
      "ছত্রাক মাত্র"
    ],
    "image": null,
    "optionImages": null,
    "timeLimit": 45
  },
  {
    "id": "hsc-biology-1st-paper-chapter-04-set-10-q13",
    "subject": "biology-1st-paper",
    "chapter": "hsc-biology-1st-paper-chapter-04-set-10",
    "text": "নিচের প্রশ্নটির সঠিক উত্তর দাও — HIV-তে কোন এনজাইম থাকে?",
    "options": [
      "অ্যামাইলেজ",
      "রিভার্স ট্রান্সক্রিপ্টেজ",
      "লাইপেজ",
      "পেপসিন"
    ],
    "image": null,
    "optionImages": null,
    "timeLimit": 45
  },
  {
    "id": "hsc-biology-1st-paper-chapter-04-set-10-q14",
    "subject": "biology-1st-paper",
    "chapter": "hsc-biology-1st-paper-chapter-04-set-10",
    "text": "নিচের প্রশ্নটির সঠিক উত্তর দাও — কলেরা রোগের জীবাণু কোনটি?",
    "options": [
      "TMV",
      "Plasmodium",
      "Vibrio cholerae",
      "Penicillium"
    ],
    "image": null,
    "optionImages": null,
    "timeLimit": 45
  },
  {
    "id": "hsc-biology-1st-paper-chapter-04-set-10-q15",
    "subject": "biology-1st-paper",
    "chapter": "hsc-biology-1st-paper-chapter-04-set-10",
    "text": "নিচের প্রশ্নটির সঠিক উত্তর দাও — ডেঙ্গু রোগের বাহক কোনটি?",
    "options": [
      "মাছি",
      "Aedes মশা",
      "Culex মশা",
      "Anopheles মশা"
    ],
    "image": null,
    "optionImages": null,
    "timeLimit": 45
  },
  {
    "id": "hsc-biology-1st-paper-chapter-04-set-10-q16",
    "subject": "biology-1st-paper",
    "chapter": "hsc-biology-1st-paper-chapter-04-set-10",
    "text": "নিচের প্রশ্নটির সঠিক উত্তর দাও — দণ্ডাকার ভাইরাসের উদাহরণ কোনটি?",
    "options": [
      "HIV",
      "T₂ phage",
      "TMV",
      "Vaccinia"
    ],
    "image": null,
    "optionImages": null,
    "timeLimit": 45
  },
  {
    "id": "hsc-biology-1st-paper-chapter-04-set-10-q17",
    "subject": "biology-1st-paper",
    "chapter": "hsc-biology-1st-paper-chapter-04-set-10",
    "text": "নিচের প্রশ্নটির সঠিক উত্তর দাও — ফায ভাইরাস সাধারণত কাকে আক্রমণ করে?",
    "options": [
      "ফার্ন",
      "শৈবাল",
      "ব্যাকটেরিয়া",
      "ছত্রাক"
    ],
    "image": null,
    "optionImages": null,
    "timeLimit": 45
  },
  {
    "id": "hsc-biology-1st-paper-chapter-04-set-10-q18",
    "subject": "biology-1st-paper",
    "chapter": "hsc-biology-1st-paper-chapter-04-set-10",
    "text": "নিচের প্রশ্নটির সঠিক উত্তর দাও — ব্যাকটেরিয়ার cell wall প্রধানত কী দিয়ে গঠিত?",
    "options": [
      "সেলুলোজ",
      "কাইটিন",
      "লিগনিন",
      "পেপটিডোগ্লাইকান"
    ],
    "image": null,
    "optionImages": null,
    "timeLimit": 45
  },
  {
    "id": "hsc-biology-1st-paper-chapter-04-set-10-q19",
    "subject": "biology-1st-paper",
    "chapter": "hsc-biology-1st-paper-chapter-04-set-10",
    "text": "নিচের প্রশ্নটির সঠিক উত্তর দাও — ব্যাকটেরিয়ার রাইবোজোমের ধরন কোনটি?",
    "options": [
      "70S",
      "40S",
      "80S",
      "60S"
    ],
    "image": null,
    "optionImages": null,
    "timeLimit": 45
  },
  {
    "id": "hsc-biology-1st-paper-chapter-04-set-10-q20",
    "subject": "biology-1st-paper",
    "chapter": "hsc-biology-1st-paper-chapter-04-set-10",
    "text": "নিচের প্রশ্নটির সঠিক উত্তর দাও — ব্যাকটেরিয়ার স্বাধীন বৃত্তাকার DNA অংশ কী?",
    "options": [
      "প্লাজমিড",
      "রাইবোজোম",
      "ক্রোমাটিড",
      "নিউক্লিওলাস"
    ],
    "image": null,
    "optionImages": null,
    "timeLimit": 45
  },
  {
    "id": "hsc-biology-1st-paper-chapter-04-set-10-q21",
    "subject": "biology-1st-paper",
    "chapter": "hsc-biology-1st-paper-chapter-04-set-10",
    "text": "নিচের প্রশ্নটির সঠিক উত্তর দাও — ভাইরাস কেন obligate parasite?",
    "options": [
      "কোষপ্রাচীর আছে",
      "শ্বসন করে",
      "নিজে খাদ্য তৈরি করে",
      "জীবন্ত কোষ ছাড়া বংশবৃদ্ধি করতে পারে না"
    ],
    "image": null,
    "optionImages": null,
    "timeLimit": 45
  },
  {
    "id": "hsc-biology-1st-paper-chapter-04-set-10-q22",
    "subject": "biology-1st-paper",
    "chapter": "hsc-biology-1st-paper-chapter-04-set-10",
    "text": "নিচের প্রশ্নটির সঠিক উত্তর দাও — ভাইরাসে সাধারণত কী থাকে?",
    "options": [
      "রাইবোজোম",
      "নিউক্লিক অ্যাসিড ও প্রোটিন কোট",
      "সেলুলোজ প্রাচীর",
      "মাইটোকন্ড্রিয়া"
    ],
    "image": null,
    "optionImages": null,
    "timeLimit": 45
  },
  {
    "id": "hsc-biology-1st-paper-chapter-04-set-10-q23",
    "subject": "biology-1st-paper",
    "chapter": "hsc-biology-1st-paper-chapter-04-set-10",
    "text": "নিচের প্রশ্নটির সঠিক উত্তর দাও — ম্যালেরিয়া জীবাণুর বহু নিউক্লিয়াসযুক্ত দশা কোনটি?",
    "options": [
      "সাইজন্ট",
      "স্পোরোজয়েট",
      "মেরোজয়েট",
      "ট্রফোজয়েট"
    ],
    "image": null,
    "optionImages": null,
    "timeLimit": 45
  },
  {
    "id": "hsc-biology-1st-paper-chapter-04-set-10-q24",
    "subject": "biology-1st-paper",
    "chapter": "hsc-biology-1st-paper-chapter-04-set-10",
    "text": "নিচের প্রশ্নটির সঠিক উত্তর দাও — ম্যালেরিয়ার জীবাণু কোনটি?",
    "options": [
      "Plasmodium",
      "E. coli",
      "TMV",
      "Vibrio cholerae"
    ],
    "image": null,
    "optionImages": null,
    "timeLimit": 45
  },
  {
    "id": "hsc-biology-1st-paper-chapter-04-set-10-q25",
    "subject": "biology-1st-paper",
    "chapter": "hsc-biology-1st-paper-chapter-04-set-10",
    "text": "নিচের প্রশ্নটির সঠিক উত্তর দাও — ম্যালেরিয়ার বাহক কোন মশা?",
    "options": [
      "স্ত্রী Anopheles",
      "পুরুষ Aedes",
      "Culex",
      "Housefly"
    ],
    "image": null,
    "optionImages": null,
    "timeLimit": 45
  }
]
